{
  "id": "data/annos/b-p-l-46-a/p32.ap.json",
  "type": "AnnotationPage",
  "items": [
    {
      "id": "https://digitalcollections.universiteitleiden.nl/iiif_manifest/item:1604565/canvas/default#anno-1",
      "type": "Annotation",
      "motivation": "supplementing",
      "body": {
        "type": "TextualBody",
        "value": "mesti pͥo q̃ ie uꝰ die. De dieu qui",
        "format": "text/plain"
      },
      "target": {
        "source": "https://digitalcollections.universiteitleiden.nl/iiif_manifest/item:1604565/canvas/default",
        "selector": {
          "type": "FragmentSelector",
          "value": "xywh=1037,451,862,158"
        }
      }
    },
    {
      "id": "https://digitalcollections.universiteitleiden.nl/iiif_manifest/item:1604565/canvas/default#anno-2",
      "type": "Annotation",
      "motivation": "supplementing",
      "body": {
        "type": "TextualBody",
        "value": "tout lemõde fourmat. Et qͥ de",
        "format": "text/plain"
      },
      "target": {
        "source": "https://digitalcollections.universiteitleiden.nl/iiif_manifest/item:1604565/canvas/default",
        "selector": {
          "type": "FragmentSelector",
          "value": "xywh=1037,586,857,104"
        }
      }
    },
    {
      "id": "https://digitalcollections.universiteitleiden.nl/iiif_manifest/item:1604565/canvas/default#anno-3",
      "type": "Annotation",
      "motivation": "supplementing",
      "body": {
        "type": "TextualBody",
        "value": "nꝰ tous la fourme at.. Ia loit",
        "format": "text/plain"
      },
      "target": {
        "source": "https://digitalcollections.universiteitleiden.nl/iiif_manifest/item:1604565/canvas/default",
        "selector": {
          "type": "FragmentSelector",
          "value": "xywh=1025,664,903,96"
        }
      }
    },
    {
      "id": "https://digitalcollections.universiteitleiden.nl/iiif_manifest/item:1604565/canvas/default#anno-4",
      "type": "Annotation",
      "motivation": "supplementing",
      "body": {
        "type": "TextualBody",
        "value": "choze q̃ oe soit dieu. Et roy del",
        "format": "text/plain"
      },
      "target": {
        "source": "https://digitalcollections.universiteitleiden.nl/iiif_manifest/item:1604565/canvas/default",
        "selector": {
          "type": "FragmentSelector",
          "value": "xywh=1040,728,839,109"
        }
      }
    },
    {
      "id": "https://digitalcollections.universiteitleiden.nl/iiif_manifest/item:1604565/canvas/default#anno-5",
      "type": "Annotation",
      "motivation": "supplementing",
      "body": {
        "type": "TextualBody",
        "value": "ciel et roy del terre. Rõ pͬ quãt",
        "format": "text/plain"
      },
      "target": {
        "source": "https://digitalcollections.universiteitleiden.nl/iiif_manifest/item:1604565/canvas/default",
        "selector": {
          "type": "FragmentSelector",
          "value": "xywh=1048,807,897,98"
        }
      }
    },
    {
      "id": "https://digitalcollections.universiteitleiden.nl/iiif_manifest/item:1604565/canvas/default#anno-6",
      "type": "Annotation",
      "motivation": "supplementing",
      "body": {
        "type": "TextualBody",
        "value": "si at la fourme. Et la sẽblãce",
        "format": "text/plain"
      },
      "target": {
        "source": "https://digitalcollections.universiteitleiden.nl/iiif_manifest/item:1604565/canvas/default",
        "selector": {
          "type": "FragmentSelector",
          "value": "xywh=1042,867,880,98"
        }
      }
    },
    {
      "id": "https://digitalcollections.universiteitleiden.nl/iiif_manifest/item:1604565/canvas/default#anno-7",
      "type": "Annotation",
      "motivation": "supplementing",
      "body": {
        "type": "TextualBody",
        "value": "pͥse del home. Tant amat hõ-",
        "format": "text/plain"
      },
      "target": {
        "source": "https://digitalcollections.universiteitleiden.nl/iiif_manifest/item:1604565/canvas/default",
        "selector": {
          "type": "FragmentSelector",
          "value": "xywh=1037,944,908,104"
        }
      }
    },
    {
      "id": "https://digitalcollections.universiteitleiden.nl/iiif_manifest/item:1604565/canvas/default#anno-8",
      "type": "Annotation",
      "motivation": "supplementing",
      "body": {
        "type": "TextualBody",
        "value": "me et tãt pͥsat. Que de luy",
        "format": "text/plain"
      },
      "target": {
        "source": "https://digitalcollections.universiteitleiden.nl/iiif_manifest/item:1604565/canvas/default",
        "selector": {
          "type": "FragmentSelector",
          "value": "xywh=1029,1018,887,105"
        }
      }
    },
    {
      "id": "https://digitalcollections.universiteitleiden.nl/iiif_manifest/item:1604565/canvas/default#anno-9",
      "type": "Annotation",
      "motivation": "supplementing",
      "body": {
        "type": "TextualBody",
        "value": "la fourme pries at. Dont",
        "format": "text/plain"
      },
      "target": {
        "source": "https://digitalcollections.universiteitleiden.nl/iiif_manifest/item:1604565/canvas/default",
        "selector": {
          "type": "FragmentSelector",
          "value": "xywh=1042,1082,827,98"
        }
      }
    },
    {
      "id": "https://digitalcollections.universiteitleiden.nl/iiif_manifest/item:1604565/canvas/default#anno-10",
      "type": "Annotation",
      "motivation": "supplementing",
      "body": {
        "type": "TextualBody",
        "value": "home se doit mlt resioiir/.",
        "format": "text/plain"
      },
      "target": {
        "source": "https://digitalcollections.universiteitleiden.nl/iiif_manifest/item:1604565/canvas/default",
        "selector": {
          "type": "FragmentSelector",
          "value": "xywh=1042,1146,812,107"
        }
      }
    },
    {
      "id": "https://digitalcollections.universiteitleiden.nl/iiif_manifest/item:1604565/canvas/default#anno-11",
      "type": "Annotation",
      "motivation": "supplementing",
      "body": {
        "type": "TextualBody",
        "value": "Cant les pere uoult deuenire",
        "format": "text/plain"
      },
      "target": {
        "source": "https://digitalcollections.universiteitleiden.nl/iiif_manifest/item:1604565/canvas/default",
        "selector": {
          "type": "FragmentSelector",
          "value": "xywh=1042,1223,908,85"
        }
      }
    },
    {
      "id": "https://digitalcollections.universiteitleiden.nl/iiif_manifest/item:1604565/canvas/default#anno-12",
      "type": "Annotation",
      "motivation": "supplementing",
      "body": {
        "type": "TextualBody",
        "value": "En flans de la u̾gne marie",
        "format": "text/plain"
      },
      "target": {
        "source": "https://digitalcollections.universiteitleiden.nl/iiif_manifest/item:1604565/canvas/default",
        "selector": {
          "type": "FragmentSelector",
          "value": "xywh=1044,1293,835,96"
        }
      }
    },
    {
      "id": "https://digitalcollections.universiteitleiden.nl/iiif_manifest/item:1604565/canvas/default#anno-13",
      "type": "Annotation",
      "motivation": "supplementing",
      "body": {
        "type": "TextualBody",
        "value": "Ky p᷑. ly fut dolãt et lier Lie",
        "format": "text/plain"
      },
      "target": {
        "source": "https://digitalcollections.universiteitleiden.nl/iiif_manifest/item:1604565/canvas/default",
        "selector": {
          "type": "FragmentSelector",
          "value": "xywh=991,1361,912,103"
        }
      }
    },
    {
      "id": "https://digitalcollections.universiteitleiden.nl/iiif_manifest/item:1604565/canvas/default#anno-14",
      "type": "Annotation",
      "motivation": "supplementing",
      "body": {
        "type": "TextualBody",
        "value": "futi quãt il soy sentit plaine",
        "format": "text/plain"
      },
      "target": {
        "source": "https://digitalcollections.universiteitleiden.nl/iiif_manifest/item:1604565/canvas/default",
        "selector": {
          "type": "FragmentSelector",
          "value": "xywh=1018,1436,910,98"
        }
      }
    },
    {
      "id": "https://digitalcollections.universiteitleiden.nl/iiif_manifest/item:1604565/canvas/default#anno-15",
      "type": "Annotation",
      "motivation": "supplementing",
      "body": {
        "type": "TextualBody",
        "value": "De la grãde deiteit humaĩe",
        "format": "text/plain"
      },
      "target": {
        "source": "https://digitalcollections.universiteitleiden.nl/iiif_manifest/item:1604565/canvas/default",
        "selector": {
          "type": "FragmentSelector",
          "value": "xywh=1037,1504,876,85"
        }
      }
    },
    {
      "id": "https://digitalcollections.universiteitleiden.nl/iiif_manifest/item:1604565/canvas/default#anno-16",
      "type": "Annotation",
      "motivation": "supplementing",
      "body": {
        "type": "TextualBody",
        "value": "Ry en son corps̃ fut a ualeie.",
        "format": "text/plain"
      },
      "target": {
        "source": "https://digitalcollections.universiteitleiden.nl/iiif_manifest/item:1604565/canvas/default",
        "selector": {
          "type": "FragmentSelector",
          "value": "xywh=1033,1585,919,77"
        }
      }
    },
    {
      "id": "https://digitalcollections.universiteitleiden.nl/iiif_manifest/item:1604565/canvas/default#anno-17",
      "type": "Annotation",
      "motivation": "supplementing",
      "body": {
        "type": "TextualBody",
        "value": "En li lueif ꝯme la roseie.",
        "format": "text/plain"
      },
      "target": {
        "source": "https://digitalcollections.universiteitleiden.nl/iiif_manifest/item:1604565/canvas/default",
        "selector": {
          "type": "FragmentSelector",
          "value": "xywh=1048,1632,814,85"
        }
      }
    },
    {
      "id": "https://digitalcollections.universiteitleiden.nl/iiif_manifest/item:1604565/canvas/default#anno-18",
      "type": "Annotation",
      "motivation": "supplementing",
      "body": {
        "type": "TextualBody",
        "value": "Uiẽt en deskẽt sor la roseie-",
        "format": "text/plain"
      },
      "target": {
        "source": "https://digitalcollections.universiteitleiden.nl/iiif_manifest/item:1604565/canvas/default",
        "selector": {
          "type": "FragmentSelector",
          "value": "xywh=1012,1692,880,83"
        }
      }
    },
    {
      "id": "https://digitalcollections.universiteitleiden.nl/iiif_manifest/item:1604565/canvas/default#anno-19",
      "type": "Annotation",
      "motivation": "supplementing",
      "body": {
        "type": "TextualBody",
        "value": "uerdeuri . Si uiẽt dieu en la",
        "format": "text/plain"
      },
      "target": {
        "source": "https://digitalcollections.universiteitleiden.nl/iiif_manifest/item:1604565/canvas/default",
        "selector": {
          "type": "FragmentSelector",
          "value": "xywh=1010,1760,874,100"
        }
      }
    },
    {
      "id": "https://digitalcollections.universiteitleiden.nl/iiif_manifest/item:1604565/canvas/default#anno-20",
      "type": "Annotation",
      "motivation": "supplementing",
      "body": {
        "type": "TextualBody",
        "value": "u̾gne pure. Qui pau ne grẽs",
        "format": "text/plain"
      },
      "target": {
        "source": "https://digitalcollections.universiteitleiden.nl/iiif_manifest/item:1604565/canvas/default",
        "selector": {
          "type": "FragmentSelector",
          "value": "xywh=1014,1817,931,107"
        }
      }
    },
    {
      "id": "https://digitalcollections.universiteitleiden.nl/iiif_manifest/item:1604565/canvas/default#anno-21",
      "type": "Annotation",
      "motivation": "supplementing",
      "body": {
        "type": "TextualBody",
        "value": "ne fut blechie. De ce futi mlt",
        "format": "text/plain"
      },
      "target": {
        "source": "https://digitalcollections.universiteitleiden.nl/iiif_manifest/item:1604565/canvas/default",
        "selector": {
          "type": "FragmentSelector",
          "value": "xywh=1048,1881,878,100"
        }
      }
    },
    {
      "id": "https://digitalcollections.universiteitleiden.nl/iiif_manifest/item:1604565/canvas/default#anno-22",
      "type": "Annotation",
      "motivation": "supplementing",
      "body": {
        "type": "TextualBody",
        "value": "Ioanti eti lie. Maĩs puis en",
        "format": "text/plain"
      },
      "target": {
        "source": "https://digitalcollections.universiteitleiden.nl/iiif_manifest/item:1604565/canvas/default",
        "selector": {
          "type": "FragmentSelector",
          "value": "xywh=1048,1956,838,91"
        }
      }
    },
    {
      "id": "https://digitalcollections.universiteitleiden.nl/iiif_manifest/item:1604565/canvas/default#anno-23",
      "type": "Annotation",
      "motivation": "supplementing",
      "body": {
        "type": "TextualBody",
        "value": "fut triste et dolant. En si",
        "format": "text/plain"
      },
      "target": {
        "source": "https://digitalcollections.universiteitleiden.nl/iiif_manifest/item:1604565/canvas/default",
        "selector": {
          "type": "FragmentSelector",
          "value": "xywh=1055,2018,824,110"
        }
      }
    },
    {
      "id": "https://digitalcollections.universiteitleiden.nl/iiif_manifest/item:1604565/canvas/default#anno-24",
      "type": "Annotation",
      "motivation": "supplementing",
      "body": {
        "type": "TextualBody",
        "value": "q̃ saĩt englize chãte. De chu",
        "format": "text/plain"
      },
      "target": {
        "source": "https://digitalcollections.universiteitleiden.nl/iiif_manifest/item:1604565/canvas/default",
        "selector": {
          "type": "FragmentSelector",
          "value": "xywh=1057,2092,850,109"
        }
      }
    },
    {
      "id": "https://digitalcollections.universiteitleiden.nl/iiif_manifest/item:1604565/canvas/default#anno-25",
      "type": "Annotation",
      "motivation": "supplementing",
      "body": {
        "type": "TextualBody",
        "value": "q̃ il le uiti en crois pẽdre.",
        "format": "text/plain"
      },
      "target": {
        "source": "https://digitalcollections.universiteitleiden.nl/iiif_manifest/item:1604565/canvas/default",
        "selector": {
          "type": "FragmentSelector",
          "value": "xywh=1059,2169,801,92"
        }
      }
    },
    {
      "id": "https://digitalcollections.universiteitleiden.nl/iiif_manifest/item:1604565/canvas/default#anno-26",
      "type": "Annotation",
      "motivation": "supplementing",
      "body": {
        "type": "TextualBody",
        "value": "Ses pies et les maĩs estẽdre",
        "format": "text/plain"
      },
      "target": {
        "source": "https://digitalcollections.universiteitleiden.nl/iiif_manifest/item:1604565/canvas/default",
        "selector": {
          "type": "FragmentSelector",
          "value": "xywh=1035,2233,893,98"
        }
      }
    },
    {
      "id": "https://digitalcollections.universiteitleiden.nl/iiif_manifest/item:1604565/canvas/default#anno-27",
      "type": "Annotation",
      "motivation": "supplementing",
      "body": {
        "type": "TextualBody",
        "value": "Et clafichier et c̾oneir/ Et en",
        "format": "text/plain"
      },
      "target": {
        "source": "https://digitalcollections.universiteitleiden.nl/iiif_manifest/item:1604565/canvas/default",
        "selector": {
          "type": "FragmentSelector",
          "value": "xywh=1050,2314,868,98"
        }
      }
    },
    {
      "id": "https://digitalcollections.universiteitleiden.nl/iiif_manifest/item:1604565/canvas/default#anno-28",
      "type": "Annotation",
      "motivation": "supplementing",
      "body": {
        "type": "TextualBody",
        "value": "la crois morti en dureir/.",
        "format": "text/plain"
      },
      "target": {
        "source": "https://digitalcollections.universiteitleiden.nl/iiif_manifest/item:1604565/canvas/default",
        "selector": {
          "type": "FragmentSelector",
          "value": "xywh=1046,2382,814,98"
        }
      }
    },
    {
      "id": "https://digitalcollections.universiteitleiden.nl/iiif_manifest/item:1604565/canvas/default#anno-29",
      "type": "Annotation",
      "motivation": "supplementing",
      "body": {
        "type": "TextualBody",
        "value": "⁊ais or en est lie et en grãde",
        "format": "text/plain"
      },
      "target": {
        "source": "https://digitalcollections.universiteitleiden.nl/iiif_manifest/item:1604565/canvas/default",
        "selector": {
          "type": "FragmentSelector",
          "value": "xywh=982,2444,953,109"
        }
      }
    },
    {
      "id": "https://digitalcollections.universiteitleiden.nl/iiif_manifest/item:1604565/canvas/default#anno-30",
      "type": "Annotation",
      "motivation": "supplementing",
      "body": {
        "type": "TextualBody",
        "value": "ioie. La ou ses douls fils le cõ",
        "format": "text/plain"
      },
      "target": {
        "source": "https://digitalcollections.universiteitleiden.nl/iiif_manifest/item:1604565/canvas/default",
        "selector": {
          "type": "FragmentSelector",
          "value": "xywh=1031,2518,908,105"
        }
      }
    },
    {
      "id": "https://digitalcollections.universiteitleiden.nl/iiif_manifest/item:1604565/canvas/default#anno-31",
      "type": "Annotation",
      "motivation": "supplementing",
      "body": {
        "type": "TextualBody",
        "value": "ioie . En tuit ly saĩs de para-",
        "format": "text/plain"
      },
      "target": {
        "source": "https://digitalcollections.universiteitleiden.nl/iiif_manifest/item:1604565/canvas/default",
        "selector": {
          "type": "FragmentSelector",
          "value": "xywh=1042,2593,889,98"
        }
      }
    },
    {
      "id": "https://digitalcollections.universiteitleiden.nl/iiif_manifest/item:1604565/canvas/default#anno-32",
      "type": "Annotation",
      "motivation": "supplementing",
      "body": {
        "type": "TextualBody",
        "value": "dis . Chascũs le sieruent par",
        "format": "text/plain"
      },
      "target": {
        "source": "https://digitalcollections.universiteitleiden.nl/iiif_manifest/item:1604565/canvas/default",
        "selector": {
          "type": "FragmentSelector",
          "value": "xywh=1057,2659,893,107"
        }
      }
    },
    {
      "id": "https://digitalcollections.universiteitleiden.nl/iiif_manifest/item:1604565/canvas/default#anno-33",
      "type": "Annotation",
      "motivation": "supplementing",
      "body": {
        "type": "TextualBody",
        "value": "estrif. Or uoilhe uenire",
        "format": "text/plain"
      },
      "target": {
        "source": "https://digitalcollections.universiteitleiden.nl/iiif_manifest/item:1604565/canvas/default",
        "selector": {
          "type": "FragmentSelector",
          "value": "xywh=1057,2727,820,94"
        }
      }
    },
    {
      "id": "https://digitalcollections.universiteitleiden.nl/iiif_manifest/item:1604565/canvas/default#anno-34",
      "type": "Annotation",
      "motivation": "supplementing",
      "body": {
        "type": "TextualBody",
        "value": "amõ traitiet. Que ie aie",
        "format": "text/plain"
      },
      "target": {
        "source": "https://digitalcollections.universiteitleiden.nl/iiif_manifest/item:1604565/canvas/default",
        "selector": {
          "type": "FragmentSelector",
          "value": "xywh=1059,2800,816,91"
        }
      }
    },
    {
      "id": "https://digitalcollections.universiteitleiden.nl/iiif_manifest/item:1604565/canvas/default#anno-35",
      "type": "Annotation",
      "motivation": "supplementing",
      "body": {
        "type": "TextualBody",
        "value": "pẽseit et ditiet. Que dien",
        "format": "text/plain"
      },
      "target": {
        "source": "https://digitalcollections.universiteitleiden.nl/iiif_manifest/item:1604565/canvas/default",
        "selector": {
          "type": "FragmentSelector",
          "value": "xywh=1067,2870,832,113"
        }
      }
    },
    {
      "id": "https://digitalcollections.universiteitleiden.nl/iiif_manifest/item:1604565/canvas/default#anno-36",
      "type": "Annotation",
      "motivation": "supplementing",
      "body": {
        "type": "TextualBody",
        "value": "ca",
        "format": "text/plain"
      },
      "target": {
        "source": "https://digitalcollections.universiteitleiden.nl/iiif_manifest/item:1604565/canvas/default",
        "selector": {
          "type": "FragmentSelector",
          "value": "xywh=1074,3122,172,115"
        }
      }
    },
    {
      "id": "https://digitalcollections.universiteitleiden.nl/iiif_manifest/item:1604565/canvas/default#anno-37",
      "type": "Annotation",
      "motivation": "supplementing",
      "body": {
        "type": "TextualBody",
        "value": "ueults tenire la court. Lỹ ue",
        "format": "text/plain"
      },
      "target": {
        "source": "https://digitalcollections.universiteitleiden.nl/iiif_manifest/item:1604565/canvas/default",
        "selector": {
          "type": "FragmentSelector",
          "value": "xywh=2056,470,800,148"
        }
      }
    },
    {
      "id": "https://digitalcollections.universiteitleiden.nl/iiif_manifest/item:1604565/canvas/default#anno-38",
      "type": "Annotation",
      "motivation": "supplementing",
      "body": {
        "type": "TextualBody",
        "value": "nire y ueult si acourt Cestiala",
        "format": "text/plain"
      },
      "target": {
        "source": "https://digitalcollections.universiteitleiden.nl/iiif_manifest/item:1604565/canvas/default",
        "selector": {
          "type": "FragmentSelector",
          "value": "xywh=2075,577,800,111"
        }
      }
    },
    {
      "id": "https://digitalcollections.universiteitleiden.nl/iiif_manifest/item:1604565/canvas/default#anno-39",
      "type": "Annotation",
      "motivation": "supplementing",
      "body": {
        "type": "TextualBody",
        "value": "fiest de tous les saĩs. Chascũs",
        "format": "text/plain"
      },
      "target": {
        "source": "https://digitalcollections.universiteitleiden.nl/iiif_manifest/item:1604565/canvas/default",
        "selector": {
          "type": "FragmentSelector",
          "value": "xywh=2093,652,775,102"
        }
      }
    },
    {
      "id": "https://digitalcollections.universiteitleiden.nl/iiif_manifest/item:1604565/canvas/default#anno-40",
      "type": "Annotation",
      "motivation": "supplementing",
      "body": {
        "type": "TextualBody",
        "value": "uinti qͥ amis atẽte. Augrãde",
        "format": "text/plain"
      },
      "target": {
        "source": "https://digitalcollections.universiteitleiden.nl/iiif_manifest/item:1604565/canvas/default",
        "selector": {
          "type": "FragmentSelector",
          "value": "xywh=2063,728,790,118"
        }
      }
    },
    {
      "id": "https://digitalcollections.universiteitleiden.nl/iiif_manifest/item:1604565/canvas/default#anno-41",
      "type": "Annotation",
      "motivation": "supplementing",
      "body": {
        "type": "TextualBody",
        "value": "pas et alõge niãbeye. Du il",
        "format": "text/plain"
      },
      "target": {
        "source": "https://digitalcollections.universiteitleiden.nl/iiif_manifest/item:1604565/canvas/default",
        "selector": {
          "type": "FragmentSelector",
          "value": "xywh=2090,803,761,111"
        }
      }
    },
    {
      "id": "https://digitalcollections.universiteitleiden.nl/iiif_manifest/item:1604565/canvas/default#anno-42",
      "type": "Annotation",
      "motivation": "supplementing",
      "body": {
        "type": "TextualBody",
        "value": "aie eylhe en peneie . Caridien",
        "format": "text/plain"
      },
      "target": {
        "source": "https://digitalcollections.universiteitleiden.nl/iiif_manifest/item:1604565/canvas/default",
        "selector": {
          "type": "FragmentSelector",
          "value": "xywh=2101,873,772,107"
        }
      }
    },
    {
      "id": "https://digitalcollections.universiteitleiden.nl/iiif_manifest/item:1604565/canvas/default#anno-43",
      "type": "Annotation",
      "motivation": "supplementing",
      "body": {
        "type": "TextualBody",
        "value": "se uolrat mlt hasteir/. Et si",
        "format": "text/plain"
      },
      "target": {
        "source": "https://digitalcollections.universiteitleiden.nl/iiif_manifest/item:1604565/canvas/default",
        "selector": {
          "type": "FragmentSelector",
          "value": "xywh=2095,946,756,102"
        }
      }
    },
    {
      "id": "https://digitalcollections.universiteitleiden.nl/iiif_manifest/item:1604565/canvas/default#anno-44",
      "type": "Annotation",
      "motivation": "supplementing",
      "body": {
        "type": "TextualBody",
        "value": "ueult lauoir et tãlteir. Ay",
        "format": "text/plain"
      },
      "target": {
        "source": "https://digitalcollections.universiteitleiden.nl/iiif_manifest/item:1604565/canvas/default",
        "selector": {
          "type": "FragmentSelector",
          "value": "xywh=2061,1014,799,109"
        }
      }
    },
    {
      "id": "https://digitalcollections.universiteitleiden.nl/iiif_manifest/item:1604565/canvas/default#anno-45",
      "type": "Annotation",
      "motivation": "supplementing",
      "body": {
        "type": "TextualBody",
        "value": "queils sont sospͥs de samour",
        "format": "text/plain"
      },
      "target": {
        "source": "https://digitalcollections.universiteitleiden.nl/iiif_manifest/item:1604565/canvas/default",
        "selector": {
          "type": "FragmentSelector",
          "value": "xywh=2097,1088,754,99"
        }
      }
    },
    {
      "id": "https://digitalcollections.universiteitleiden.nl/iiif_manifest/item:1604565/canvas/default#anno-46",
      "type": "Annotation",
      "motivation": "supplementing",
      "body": {
        "type": "TextualBody",
        "value": "Iluellemẽt et ẜ loriõs. Il en",
        "format": "text/plain"
      },
      "target": {
        "source": "https://digitalcollections.universiteitleiden.nl/iiif_manifest/item:1604565/canvas/default",
        "selector": {
          "type": "FragmentSelector",
          "value": "xywh=2061,1161,801,121"
        }
      }
    },
    {
      "id": "https://digitalcollections.universiteitleiden.nl/iiif_manifest/item:1604565/canvas/default#anno-47",
      "type": "Annotation",
      "motivation": "supplementing",
      "body": {
        "type": "TextualBody",
        "value": "apelle ẜ symõ . Kil ne tient",
        "format": "text/plain"
      },
      "target": {
        "source": "https://digitalcollections.universiteitleiden.nl/iiif_manifest/item:1604565/canvas/default",
        "selector": {
          "type": "FragmentSelector",
          "value": "xywh=2073,1236,789,100"
        }
      }
    },
    {
      "id": "https://digitalcollections.universiteitleiden.nl/iiif_manifest/item:1604565/canvas/default#anno-48",
      "type": "Annotation",
      "motivation": "supplementing",
      "body": {
        "type": "TextualBody",
        "value": "pas a en fanchons. Saĩs iud",
        "format": "text/plain"
      },
      "target": {
        "source": "https://digitalcollections.universiteitleiden.nl/iiif_manifest/item:1604565/canvas/default",
        "selector": {
          "type": "FragmentSelector",
          "value": "xywh=2095,1308,782,102"
        }
      }
    },
    {
      "id": "https://digitalcollections.universiteitleiden.nl/iiif_manifest/item:1604565/canvas/default#anno-49",
      "type": "Annotation",
      "motivation": "supplementing",
      "body": {
        "type": "TextualBody",
        "value": "nobliat mie. Aus les a uois",
        "format": "text/plain"
      },
      "target": {
        "source": "https://digitalcollections.universiteitleiden.nl/iiif_manifest/item:1604565/canvas/default",
        "selector": {
          "type": "FragmentSelector",
          "value": "xywh=2084,1372,786,102"
        }
      }
    },
    {
      "id": "https://digitalcollections.universiteitleiden.nl/iiif_manifest/item:1604565/canvas/default#anno-50",
      "type": "Annotation",
      "motivation": "supplementing",
      "body": {
        "type": "TextualBody",
        "value": "serie. Beneis auãt mes bõs",
        "format": "text/plain"
      },
      "target": {
        "source": "https://digitalcollections.universiteitleiden.nl/iiif_manifest/item:1604565/canvas/default",
        "selector": {
          "type": "FragmentSelector",
          "value": "xywh=2101,1442,774,92"
        }
      }
    },
    {
      "id": "https://digitalcollections.universiteitleiden.nl/iiif_manifest/item:1604565/canvas/default#anno-51",
      "type": "Annotation",
      "motivation": "supplementing",
      "body": {
        "type": "TextualBody",
        "value": "amis. Et li parleis un pau",
        "format": "text/plain"
      },
      "target": {
        "source": "https://digitalcollections.universiteitleiden.nl/iiif_manifest/item:1604565/canvas/default",
        "selector": {
          "type": "FragmentSelector",
          "value": "xywh=2103,1500,763,102"
        }
      }
    },
    {
      "id": "https://digitalcollections.universiteitleiden.nl/iiif_manifest/item:1604565/canvas/default#anno-52",
      "type": "Annotation",
      "motivation": "supplementing",
      "body": {
        "type": "TextualBody",
        "value": "ami. Alleis en tost ꝑ ces del",
        "format": "text/plain"
      },
      "target": {
        "source": "https://digitalcollections.universiteitleiden.nl/iiif_manifest/item:1604565/canvas/default",
        "selector": {
          "type": "FragmentSelector",
          "value": "xywh=2101,1562,789,106"
        }
      }
    },
    {
      "id": "https://digitalcollections.universiteitleiden.nl/iiif_manifest/item:1604565/canvas/default#anno-53",
      "type": "Annotation",
      "motivation": "supplementing",
      "body": {
        "type": "TextualBody",
        "value": "trois . ꝑchãbre et ꝑ refreton",
        "format": "text/plain"
      },
      "target": {
        "source": "https://digitalcollections.universiteitleiden.nl/iiif_manifest/item:1604565/canvas/default",
        "selector": {
          "type": "FragmentSelector",
          "value": "xywh=2103,1640,791,105"
        }
      }
    },
    {
      "id": "https://digitalcollections.universiteitleiden.nl/iiif_manifest/item:1604565/canvas/default#anno-54",
      "type": "Annotation",
      "motivation": "supplementing",
      "body": {
        "type": "TextualBody",
        "value": "Somõneis lous laĩs et toul",
        "format": "text/plain"
      },
      "target": {
        "source": "https://digitalcollections.universiteitleiden.nl/iiif_manifest/item:1604565/canvas/default",
        "selector": {
          "type": "FragmentSelector",
          "value": "xywh=2101,1700,789,109"
        }
      }
    },
    {
      "id": "https://digitalcollections.universiteitleiden.nl/iiif_manifest/item:1604565/canvas/default#anno-55",
      "type": "Annotation",
      "motivation": "supplementing",
      "body": {
        "type": "TextualBody",
        "value": "saĩt. Dont/ il y at et maĩs et",
        "format": "text/plain"
      },
      "target": {
        "source": "https://digitalcollections.universiteitleiden.nl/iiif_manifest/item:1604565/canvas/default",
        "selector": {
          "type": "FragmentSelector",
          "value": "xywh=2101,1768,778,105"
        }
      }
    },
    {
      "id": "https://digitalcollections.universiteitleiden.nl/iiif_manifest/item:1604565/canvas/default#anno-56",
      "type": "Annotation",
      "motivation": "supplementing",
      "body": {
        "type": "TextualBody",
        "value": "maĩt. Gardeis q̃ nuls ny re",
        "format": "text/plain"
      },
      "target": {
        "source": "https://digitalcollections.universiteitleiden.nl/iiif_manifest/item:1604565/canvas/default",
        "selector": {
          "type": "FragmentSelector",
          "value": "xywh=2084,1841,784,91"
        }
      }
    },
    {
      "id": "https://digitalcollections.universiteitleiden.nl/iiif_manifest/item:1604565/canvas/default#anno-57",
      "type": "Annotation",
      "motivation": "supplementing",
      "body": {
        "type": "TextualBody",
        "value": "maĩti. Chascũs amaine la ꝯ",
        "format": "text/plain"
      },
      "target": {
        "source": "https://digitalcollections.universiteitleiden.nl/iiif_manifest/item:1604565/canvas/default",
        "selector": {
          "type": "FragmentSelector",
          "value": "xywh=2090,1905,785,100"
        }
      }
    },
    {
      "id": "https://digitalcollections.universiteitleiden.nl/iiif_manifest/item:1604565/canvas/default#anno-58",
      "type": "Annotation",
      "motivation": "supplementing",
      "body": {
        "type": "TextualBody",
        "value": "paingne. Tous les ꝯpaĩgnõt",
        "format": "text/plain"
      },
      "target": {
        "source": "https://digitalcollections.universiteitleiden.nl/iiif_manifest/item:1604565/canvas/default",
        "selector": {
          "type": "FragmentSelector",
          "value": "xywh=2103,1971,774,104"
        }
      }
    },
    {
      "id": "https://digitalcollections.universiteitleiden.nl/iiif_manifest/item:1604565/canvas/default#anno-59",
      "type": "Annotation",
      "motivation": "supplementing",
      "body": {
        "type": "TextualBody",
        "value": "sens de lay. Si come ie di si le",
        "format": "text/plain"
      },
      "target": {
        "source": "https://digitalcollections.universiteitleiden.nl/iiif_manifest/item:1604565/canvas/default",
        "selector": {
          "type": "FragmentSelector",
          "value": "xywh=2103,2041,748,102"
        }
      }
    },
    {
      "id": "https://digitalcollections.universiteitleiden.nl/iiif_manifest/item:1604565/canvas/default#anno-60",
      "type": "Annotation",
      "motivation": "supplementing",
      "body": {
        "type": "TextualBody",
        "value": "moy fais. Dis tosti a tous les",
        "format": "text/plain"
      },
      "target": {
        "source": "https://digitalcollections.universiteitleiden.nl/iiif_manifest/item:1604565/canvas/default",
        "selector": {
          "type": "FragmentSelector",
          "value": "xywh=2095,2122,782,96"
        }
      }
    },
    {
      "id": "https://digitalcollections.universiteitleiden.nl/iiif_manifest/item:1604565/canvas/default#anno-61",
      "type": "Annotation",
      "motivation": "supplementing",
      "body": {
        "type": "TextualBody",
        "value": "ꝯtre dire . Ke tenire uoilhe",
        "format": "text/plain"
      },
      "target": {
        "source": "https://digitalcollections.universiteitleiden.nl/iiif_manifest/item:1604565/canvas/default",
        "selector": {
          "type": "FragmentSelector",
          "value": "xywh=2099,2186,733,100"
        }
      }
    },
    {
      "id": "https://digitalcollections.universiteitleiden.nl/iiif_manifest/item:1604565/canvas/default#anno-62",
      "type": "Annotation",
      "motivation": "supplementing",
      "body": {
        "type": "TextualBody",
        "value": "court a droit hẽ. Elle mois",
        "format": "text/plain"
      },
      "target": {
        "source": "https://digitalcollections.universiteitleiden.nl/iiif_manifest/item:1604565/canvas/default",
        "selector": {
          "type": "FragmentSelector",
          "value": "xywh=2101,2256,738,96"
        }
      }
    },
    {
      "id": "https://digitalcollections.universiteitleiden.nl/iiif_manifest/item:1604565/canvas/default#anno-63",
      "type": "Annotation",
      "motivation": "supplementing",
      "body": {
        "type": "TextualBody",
        "value": "apõ le ẜ recay. Uoilhe q̃ tous",
        "format": "text/plain"
      },
      "target": {
        "source": "https://digitalcollections.universiteitleiden.nl/iiif_manifest/item:1604565/canvas/default",
        "selector": {
          "type": "FragmentSelector",
          "value": "xywh=2107,2320,761,103"
        }
      }
    },
    {
      "id": "https://digitalcollections.universiteitleiden.nl/iiif_manifest/item:1604565/canvas/default#anno-64",
      "type": "Annotation",
      "motivation": "supplementing",
      "body": {
        "type": "TextualBody",
        "value": "loiẽt deuãt my. Car tenirl",
        "format": "text/plain"
      },
      "target": {
        "source": "https://digitalcollections.universiteitleiden.nl/iiif_manifest/item:1604565/canvas/default",
        "selector": {
          "type": "FragmentSelector",
          "value": "xywh=2107,2395,757,94"
        }
      }
    },
    {
      "id": "https://digitalcollections.universiteitleiden.nl/iiif_manifest/item:1604565/canvas/default#anno-65",
      "type": "Annotation",
      "motivation": "supplementing",
      "body": {
        "type": "TextualBody",
        "value": "uoray ma court grãde.",
        "format": "text/plain"
      },
      "target": {
        "source": "https://digitalcollections.universiteitleiden.nl/iiif_manifest/item:1604565/canvas/default",
        "selector": {
          "type": "FragmentSelector",
          "value": "xywh=2090,2476,723,89"
        }
      }
    },
    {
      "id": "https://digitalcollections.universiteitleiden.nl/iiif_manifest/item:1604565/canvas/default#anno-66",
      "type": "Annotation",
      "motivation": "supplementing",
      "body": {
        "type": "TextualBody",
        "value": "Saĩs lymõ at leueit la ch̾i",
        "format": "text/plain"
      },
      "target": {
        "source": "https://digitalcollections.universiteitleiden.nl/iiif_manifest/item:1604565/canvas/default",
        "selector": {
          "type": "FragmentSelector",
          "value": "xywh=2118,2540,752,91"
        }
      }
    },
    {
      "id": "https://digitalcollections.universiteitleiden.nl/iiif_manifest/item:1604565/canvas/default#anno-67",
      "type": "Annotation",
      "motivation": "supplementing",
      "body": {
        "type": "TextualBody",
        "value": "Nm̃eẜ ; respõdi. Sire dedẽs ael",
        "format": "text/plain"
      },
      "target": {
        "source": "https://digitalcollections.universiteitleiden.nl/iiif_manifest/item:1604565/canvas/default",
        "selector": {
          "type": "FragmentSelector",
          "value": "xywh=2090,2604,789,96"
        }
      }
    },
    {
      "id": "https://digitalcollections.universiteitleiden.nl/iiif_manifest/item:1604565/canvas/default#anno-68",
      "type": "Annotation",
      "motivation": "supplementing",
      "body": {
        "type": "TextualBody",
        "value": "semdy. Ulrõs nꝰ fait chu qͣl",
        "format": "text/plain"
      },
      "target": {
        "source": "https://digitalcollections.universiteitleiden.nl/iiif_manifest/item:1604565/canvas/default",
        "selector": {
          "type": "FragmentSelector",
          "value": "xywh=2105,2672,727,96"
        }
      }
    },
    {
      "id": "https://digitalcollections.universiteitleiden.nl/iiif_manifest/item:1604565/canvas/default#anno-69",
      "type": "Annotation",
      "motivation": "supplementing",
      "body": {
        "type": "TextualBody",
        "value": "roueis. Ia uns seule ny lie",
        "format": "text/plain"
      },
      "target": {
        "source": "https://digitalcollections.universiteitleiden.nl/iiif_manifest/item:1604565/canvas/default",
        "selector": {
          "type": "FragmentSelector",
          "value": "xywh=2093,2738,754,107"
        }
      }
    },
    {
      "id": "https://digitalcollections.universiteitleiden.nl/iiif_manifest/item:1604565/canvas/default#anno-70",
      "type": "Annotation",
      "motivation": "supplementing",
      "body": {
        "type": "TextualBody",
        "value": "tͦueis. Ry ne loit lomoñs e",
        "format": "text/plain"
      },
      "target": {
        "source": "https://digitalcollections.universiteitleiden.nl/iiif_manifest/item:1604565/canvas/default",
        "selector": {
          "type": "FragmentSelector",
          "value": "xywh=2107,2802,755,106"
        }
      }
    },
    {
      "id": "https://digitalcollections.universiteitleiden.nl/iiif_manifest/item:1604565/canvas/default#anno-71",
      "type": "Annotation",
      "motivation": "supplementing",
      "body": {
        "type": "TextualBody",
        "value": "tre saiet. Atãt nr̃e s. le laitl",
        "format": "text/plain"
      },
      "target": {
        "source": "https://digitalcollections.universiteitleiden.nl/iiif_manifest/item:1604565/canvas/default",
        "selector": {
          "type": "FragmentSelector",
          "value": "xywh=2105,2872,759,120"
        }
      }
    },
    {
      "id": "https://digitalcollections.universiteitleiden.nl/iiif_manifest/item:1604565/canvas/default#anno-72",
      "type": "Annotation",
      "motivation": "supplementing",
      "body": {
        "type": "TextualBody",
        "value": "4",
        "format": "text/plain"
      },
      "target": {
        "source": "https://digitalcollections.universiteitleiden.nl/iiif_manifest/item:1604565/canvas/default",
        "selector": {
          "type": "FragmentSelector",
          "value": "xywh=2176,3151,102,115"
        }
      }
    },
    {
      "id": "https://digitalcollections.universiteitleiden.nl/iiif_manifest/item:1604565/canvas/default#anno-73",
      "type": "Annotation",
      "motivation": "supplementing",
      "body": {
        "type": "TextualBody",
        "value": "cu",
        "format": "text/plain"
      },
      "target": {
        "source": "https://digitalcollections.universiteitleiden.nl/iiif_manifest/item:1604565/canvas/default",
        "selector": {
          "type": "FragmentSelector",
          "value": "xywh=2593,3190,130,59"
        }
      }
    },
    {
      "id": "https://digitalcollections.universiteitleiden.nl/iiif_manifest/item:1604565/canvas/default#anno-74",
      "type": "Annotation",
      "motivation": "supplementing",
      "body": {
        "type": "TextualBody",
        "value": ".ccc .xx.",
        "format": "text/plain"
      },
      "target": {
        "source": "https://digitalcollections.universiteitleiden.nl/iiif_manifest/item:1604565/canvas/default",
        "selector": {
          "type": "FragmentSelector",
          "value": "xywh=4676,340,226,92"
        }
      }
    },
    {
      "id": "https://digitalcollections.universiteitleiden.nl/iiif_manifest/item:1604565/canvas/default#anno-75",
      "type": "Annotation",
      "motivation": "supplementing",
      "body": {
        "type": "TextualBody",
        "value": "11",
        "format": "text/plain"
      },
      "target": {
        "source": "https://digitalcollections.universiteitleiden.nl/iiif_manifest/item:1604565/canvas/default",
        "selector": {
          "type": "FragmentSelector",
          "value": "xywh=3819,432,62,75"
        }
      }
    },
    {
      "id": "https://digitalcollections.universiteitleiden.nl/iiif_manifest/item:1604565/canvas/default#anno-76",
      "type": "Annotation",
      "motivation": "supplementing",
      "body": {
        "type": "TextualBody",
        "value": "Que plꝯ ne dilli ne ne ꝯleilhe",
        "format": "text/plain"
      },
      "target": {
        "source": "https://digitalcollections.universiteitleiden.nl/iiif_manifest/item:1604565/canvas/default",
        "selector": {
          "type": "FragmentSelector",
          "value": "xywh=3088,441,786,157"
        }
      }
    },
    {
      "id": "https://digitalcollections.universiteitleiden.nl/iiif_manifest/item:1604565/canvas/default#anno-77",
      "type": "Annotation",
      "motivation": "supplementing",
      "body": {
        "type": "TextualBody",
        "value": "Et lachies mlt uolantire yrons",
        "format": "text/plain"
      },
      "target": {
        "source": "https://digitalcollections.universiteitleiden.nl/iiif_manifest/item:1604565/canvas/default",
        "selector": {
          "type": "FragmentSelector",
          "value": "xywh=4049,439,889,161"
        }
      }
    },
    {
      "id": "https://digitalcollections.universiteitleiden.nl/iiif_manifest/item:1604565/canvas/default#anno-78",
      "type": "Annotation",
      "motivation": "supplementing",
      "body": {
        "type": "TextualBody",
        "value": "Et E lymon si sa pareilhe. E",
        "format": "text/plain"
      },
      "target": {
        "source": "https://digitalcollections.universiteitleiden.nl/iiif_manifest/item:1604565/canvas/default",
        "selector": {
          "type": "FragmentSelector",
          "value": "xywh=3086,575,754,102"
        }
      }
    },
    {
      "id": "https://digitalcollections.universiteitleiden.nl/iiif_manifest/item:1604565/canvas/default#anno-79",
      "type": "Annotation",
      "motivation": "supplementing",
      "body": {
        "type": "TextualBody",
        "value": "Fait ailhẽ. ur̃e message. Et il le",
        "format": "text/plain"
      },
      "target": {
        "source": "https://digitalcollections.universiteitleiden.nl/iiif_manifest/item:1604565/canvas/default",
        "selector": {
          "type": "FragmentSelector",
          "value": "xywh=4047,571,861,106"
        }
      }
    },
    {
      "id": "https://digitalcollections.universiteitleiden.nl/iiif_manifest/item:1604565/canvas/default#anno-80",
      "type": "Annotation",
      "motivation": "supplementing",
      "body": {
        "type": "TextualBody",
        "value": "tut ꝑ un matin młt maiti.",
        "format": "text/plain"
      },
      "target": {
        "source": "https://digitalcollections.universiteitleiden.nl/iiif_manifest/item:1604565/canvas/default",
        "selector": {
          "type": "FragmentSelector",
          "value": "xywh=3092,654,753,96"
        }
      }
    },
    {
      "id": "https://digitalcollections.universiteitleiden.nl/iiif_manifest/item:1604565/canvas/default#anno-81",
      "type": "Annotation",
      "motivation": "supplementing",
      "body": {
        "type": "TextualBody",
        "value": "faiti a loy de sage. De la sen parts",
        "format": "text/plain"
      },
      "target": {
        "source": "https://digitalcollections.universiteitleiden.nl/iiif_manifest/item:1604565/canvas/default",
        "selector": {
          "type": "FragmentSelector",
          "value": "xywh=4047,649,885,101"
        }
      }
    },
    {
      "id": "https://digitalcollections.universiteitleiden.nl/iiif_manifest/item:1604565/canvas/default#anno-82",
      "type": "Annotation",
      "motivation": "supplementing",
      "body": {
        "type": "TextualBody",
        "value": "Des eskilhet at pͥs en sa maĩ.",
        "format": "text/plain"
      },
      "target": {
        "source": "https://digitalcollections.universiteitleiden.nl/iiif_manifest/item:1604565/canvas/default",
        "selector": {
          "type": "FragmentSelector",
          "value": "xywh=3073,730,797,96"
        }
      }
    },
    {
      "id": "https://digitalcollections.universiteitleiden.nl/iiif_manifest/item:1604565/canvas/default#anno-83",
      "type": "Annotation",
      "motivation": "supplementing",
      "body": {
        "type": "TextualBody",
        "value": "isnellemẽt . Et uoit tenire cõ-",
        "format": "text/plain"
      },
      "target": {
        "source": "https://digitalcollections.universiteitleiden.nl/iiif_manifest/item:1604565/canvas/default",
        "selector": {
          "type": "FragmentSelector",
          "value": "xywh=4034,720,900,91"
        }
      }
    },
    {
      "id": "https://digitalcollections.universiteitleiden.nl/iiif_manifest/item:1604565/canvas/default#anno-84",
      "type": "Annotation",
      "motivation": "supplementing",
      "body": {
        "type": "TextualBody",
        "value": "Saĩs iude en maine auoiti ly.",
        "format": "text/plain"
      },
      "target": {
        "source": "https://digitalcollections.universiteitleiden.nl/iiif_manifest/item:1604565/canvas/default",
        "selector": {
          "type": "FragmentSelector",
          "value": "xywh=3064,790,832,102"
        }
      }
    },
    {
      "id": "https://digitalcollections.universiteitleiden.nl/iiif_manifest/item:1604565/canvas/default#anno-85",
      "type": "Annotation",
      "motivation": "supplementing",
      "body": {
        "type": "TextualBody",
        "value": "munemẽt . Les pr̃ĩarke tous",
        "format": "text/plain"
      },
      "target": {
        "source": "https://digitalcollections.universiteitleiden.nl/iiif_manifest/item:1604565/canvas/default",
        "selector": {
          "type": "FragmentSelector",
          "value": "xywh=4032,788,874,98"
        }
      }
    },
    {
      "id": "https://digitalcollections.universiteitleiden.nl/iiif_manifest/item:1604565/canvas/default#anno-86",
      "type": "Annotation",
      "motivation": "supplementing",
      "body": {
        "type": "TextualBody",
        "value": "Dilluq sen uõti ambedeu.",
        "format": "text/plain"
      },
      "target": {
        "source": "https://digitalcollections.universiteitleiden.nl/iiif_manifest/item:1604565/canvas/default",
        "selector": {
          "type": "FragmentSelector",
          "value": "xywh=3075,865,729,104"
        }
      }
    },
    {
      "id": "https://digitalcollections.universiteitleiden.nl/iiif_manifest/item:1604565/canvas/default#anno-87",
      "type": "Annotation",
      "motivation": "supplementing",
      "body": {
        "type": "TextualBody",
        "value": "en semble. ¶Dist abrahã si q̃moy",
        "format": "text/plain"
      },
      "target": {
        "source": "https://digitalcollections.universiteitleiden.nl/iiif_manifest/item:1604565/canvas/default",
        "selector": {
          "type": "FragmentSelector",
          "value": "xywh=4053,854,940,102"
        }
      }
    },
    {
      "id": "https://digitalcollections.universiteitleiden.nl/iiif_manifest/item:1604565/canvas/default#anno-88",
      "type": "Annotation",
      "motivation": "supplementing",
      "body": {
        "type": "TextualBody",
        "value": "En une chãbra lont entreis.",
        "format": "text/plain"
      },
      "target": {
        "source": "https://digitalcollections.universiteitleiden.nl/iiif_manifest/item:1604565/canvas/default",
        "selector": {
          "type": "FragmentSelector",
          "value": "xywh=3079,937,776,96"
        }
      }
    },
    {
      "id": "https://digitalcollections.universiteitleiden.nl/iiif_manifest/item:1604565/canvas/default#anno-89",
      "type": "Annotation",
      "motivation": "supplementing",
      "body": {
        "type": "TextualBody",
        "value": "senble. Que ie uoy uenire limõs.",
        "format": "text/plain"
      },
      "target": {
        "source": "https://digitalcollections.universiteitleiden.nl/iiif_manifest/item:1604565/canvas/default",
        "selector": {
          "type": "FragmentSelector",
          "value": "xywh=4051,929,932,102"
        }
      }
    },
    {
      "id": "https://digitalcollections.universiteitleiden.nl/iiif_manifest/item:1604565/canvas/default#anno-90",
      "type": "Annotation",
      "motivation": "supplementing",
      "body": {
        "type": "TextualBody",
        "value": "Tous les angele yont tͦueit",
        "format": "text/plain"
      },
      "target": {
        "source": "https://digitalcollections.universiteitleiden.nl/iiif_manifest/item:1604565/canvas/default",
        "selector": {
          "type": "FragmentSelector",
          "value": "xywh=3073,1014,793,98"
        }
      }
    },
    {
      "id": "https://digitalcollections.universiteitleiden.nl/iiif_manifest/item:1604565/canvas/default#anno-91",
      "type": "Annotation",
      "motivation": "supplementing",
      "body": {
        "type": "TextualBody",
        "value": "Or entẽdons sa raison. Et ẜ symõ",
        "format": "text/plain"
      },
      "target": {
        "source": "https://digitalcollections.universiteitleiden.nl/iiif_manifest/item:1604565/canvas/default",
        "selector": {
          "type": "FragmentSelector",
          "value": "xywh=4045,1003,925,109"
        }
      }
    },
    {
      "id": "https://digitalcollections.universiteitleiden.nl/iiif_manifest/item:1604565/canvas/default#anno-92",
      "type": "Annotation",
      "motivation": "supplementing",
      "body": {
        "type": "TextualBody",
        "value": "ky amueilhe astoiẽt bias.",
        "format": "text/plain"
      },
      "target": {
        "source": "https://digitalcollections.universiteitleiden.nl/iiif_manifest/item:1604565/canvas/default",
        "selector": {
          "type": "FragmentSelector",
          "value": "xywh=3058,1080,774,107"
        }
      }
    },
    {
      "id": "https://digitalcollections.universiteitleiden.nl/iiif_manifest/item:1604565/canvas/default#anno-93",
      "type": "Annotation",
      "motivation": "supplementing",
      "body": {
        "type": "TextualBody",
        "value": "lens atargier. Les at somouns",
        "format": "text/plain"
      },
      "target": {
        "source": "https://digitalcollections.universiteitleiden.nl/iiif_manifest/item:1604565/canvas/default",
        "selector": {
          "type": "FragmentSelector",
          "value": "xywh=4053,1080,889,92"
        }
      }
    },
    {
      "id": "https://digitalcollections.universiteitleiden.nl/iiif_manifest/item:1604565/canvas/default#anno-94",
      "type": "Annotation",
      "motivation": "supplementing",
      "body": {
        "type": "TextualBody",
        "value": "Et deuãt tos. bgabel. Ky le",
        "format": "text/plain"
      },
      "target": {
        "source": "https://digitalcollections.universiteitleiden.nl/iiif_manifest/item:1604565/canvas/default",
        "selector": {
          "type": "FragmentSelector",
          "value": "xywh=3079,1161,793,100"
        }
      }
    },
    {
      "id": "https://digitalcollections.universiteitleiden.nl/iiif_manifest/item:1604565/canvas/default#anno-95",
      "type": "Annotation",
      "motivation": "supplementing",
      "body": {
        "type": "TextualBody",
        "value": "q̃ sens dangier/. Ueĩgnẽti a cest",
        "format": "text/plain"
      },
      "target": {
        "source": "https://digitalcollections.universiteitleiden.nl/iiif_manifest/item:1604565/canvas/default",
        "selector": {
          "type": "FragmentSelector",
          "value": "xywh=4053,1148,868,102"
        }
      }
    },
    {
      "id": "https://digitalcollections.universiteitleiden.nl/iiif_manifest/item:1604565/canvas/default#anno-96",
      "type": "Annotation",
      "motivation": "supplementing",
      "body": {
        "type": "TextualBody",
        "value": "la lut dieu ap̾tati. Dõt puis",
        "format": "text/plain"
      },
      "target": {
        "source": "https://digitalcollections.universiteitleiden.nl/iiif_manifest/item:1604565/canvas/default",
        "selector": {
          "type": "FragmentSelector",
          "value": "xywh=3075,1233,789,98"
        }
      }
    },
    {
      "id": "https://digitalcollections.universiteitleiden.nl/iiif_manifest/item:1604565/canvas/default#anno-97",
      "type": "Annotation",
      "motivation": "supplementing",
      "body": {
        "type": "TextualBody",
        "value": "fiest fuire. Ghils respõdent come",
        "format": "text/plain"
      },
      "target": {
        "source": "https://digitalcollections.universiteitleiden.nl/iiif_manifest/item:1604565/canvas/default",
        "selector": {
          "type": "FragmentSelector",
          "value": "xywh=4051,1214,915,94"
        }
      }
    },
    {
      "id": "https://digitalcollections.universiteitleiden.nl/iiif_manifest/item:1604565/canvas/default#anno-98",
      "type": "Annotation",
      "motivation": "supplementing",
      "body": {
        "type": "TextualBody",
        "value": "maĩt ame ꝯfortati. Saĩs",
        "format": "text/plain"
      },
      "target": {
        "source": "https://digitalcollections.universiteitleiden.nl/iiif_manifest/item:1604565/canvas/default",
        "selector": {
          "type": "FragmentSelector",
          "value": "xywh=3056,1306,769,94"
        }
      }
    },
    {
      "id": "https://digitalcollections.universiteitleiden.nl/iiif_manifest/item:1604565/canvas/default#anno-99",
      "type": "Annotation",
      "motivation": "supplementing",
      "body": {
        "type": "TextualBody",
        "value": "de bonaire. Alleis auãt/ simons",
        "format": "text/plain"
      },
      "target": {
        "source": "https://digitalcollections.universiteitleiden.nl/iiif_manifest/item:1604565/canvas/default",
        "selector": {
          "type": "FragmentSelector",
          "value": "xywh=4056,1280,893,98"
        }
      }
    },
    {
      "id": "https://digitalcollections.universiteitleiden.nl/iiif_manifest/item:1604565/canvas/default#anno-100",
      "type": "Annotation",
      "motivation": "supplementing",
      "body": {
        "type": "TextualBody",
        "value": "mychiel auoit ly astoiti. Lũci",
        "format": "text/plain"
      },
      "target": {
        "source": "https://digitalcollections.universiteitleiden.nl/iiif_manifest/item:1604565/canvas/default",
        "selector": {
          "type": "FragmentSelector",
          "value": "xywh=3062,1372,812,94"
        }
      }
    },
    {
      "id": "https://digitalcollections.universiteitleiden.nl/iiif_manifest/item:1604565/canvas/default#anno-101",
      "type": "Annotation",
      "motivation": "supplementing",
      "body": {
        "type": "TextualBody",
        "value": "bias frere. Nos yrõs p. dieunꝰ",
        "format": "text/plain"
      },
      "target": {
        "source": "https://digitalcollections.universiteitleiden.nl/iiif_manifest/item:1604565/canvas/default",
        "selector": {
          "type": "FragmentSelector",
          "value": "xywh=4056,1348,901,101"
        }
      }
    },
    {
      "id": "https://digitalcollections.universiteitleiden.nl/iiif_manifest/item:1604565/canvas/default#anno-102",
      "type": "Annotation",
      "motivation": "supplementing",
      "body": {
        "type": "TextualBody",
        "value": "lautre ꝑ le maĩ tenoit. Et",
        "format": "text/plain"
      },
      "target": {
        "source": "https://digitalcollections.universiteitleiden.nl/iiif_manifest/item:1604565/canvas/default",
        "selector": {
          "type": "FragmentSelector",
          "value": "xywh=3075,1432,755,96"
        }
      }
    },
    {
      "id": "https://digitalcollections.universiteitleiden.nl/iiif_manifest/item:1604565/canvas/default#anno-103",
      "type": "Annotation",
      "motivation": "supplementing",
      "body": {
        "type": "TextualBody",
        "value": "uõt iowuant ꝑ ces bias liewe",
        "format": "text/plain"
      },
      "target": {
        "source": "https://digitalcollections.universiteitleiden.nl/iiif_manifest/item:1604565/canvas/default",
        "selector": {
          "type": "FragmentSelector",
          "value": "xywh=3043,1498,836,98"
        }
      }
    },
    {
      "id": "https://digitalcollections.universiteitleiden.nl/iiif_manifest/item:1604565/canvas/default#anno-104",
      "type": "Annotation",
      "motivation": "supplementing",
      "body": {
        "type": "TextualBody",
        "value": "pere. Saĩs lymõ sen deꝑtit. Ap̃s",
        "format": "text/plain"
      },
      "target": {
        "source": "https://digitalcollections.universiteitleiden.nl/iiif_manifest/item:1604565/canvas/default",
        "selector": {
          "type": "FragmentSelector",
          "value": "xywh=4056,1408,903,115"
        }
      }
    },
    {
      "id": "https://digitalcollections.universiteitleiden.nl/iiif_manifest/item:1604565/canvas/default#anno-105",
      "type": "Annotation",
      "motivation": "supplementing",
      "body": {
        "type": "TextualBody",
        "value": "deuãt lỹ chusit. Les apõsteles",
        "format": "text/plain"
      },
      "target": {
        "source": "https://digitalcollections.universiteitleiden.nl/iiif_manifest/item:1604565/canvas/default",
        "selector": {
          "type": "FragmentSelector",
          "value": "xywh=4051,1476,853,103"
        }
      }
    },
    {
      "id": "https://digitalcollections.universiteitleiden.nl/iiif_manifest/item:1604565/canvas/default#anno-106",
      "type": "Annotation",
      "motivation": "supplementing",
      "body": {
        "type": "TextualBody",
        "value": "Et ẜ simõs ly douls et ly piwe",
        "format": "text/plain"
      },
      "target": {
        "source": "https://digitalcollections.universiteitleiden.nl/iiif_manifest/item:1604565/canvas/default",
        "selector": {
          "type": "FragmentSelector",
          "value": "xywh=3073,1570,840,92"
        }
      }
    },
    {
      "id": "https://digitalcollections.universiteitleiden.nl/iiif_manifest/item:1604565/canvas/default#anno-107",
      "type": "Annotation",
      "motivation": "supplementing",
      "body": {
        "type": "TextualBody",
        "value": "les ꝯpaĩgnõs. En hault sescrie",
        "format": "text/plain"
      },
      "target": {
        "source": "https://digitalcollections.universiteitleiden.nl/iiif_manifest/item:1604565/canvas/default",
        "selector": {
          "type": "FragmentSelector",
          "value": "xywh=4051,1540,853,111"
        }
      }
    },
    {
      "id": "https://digitalcollections.universiteitleiden.nl/iiif_manifest/item:1604565/canvas/default#anno-108",
      "type": "Annotation",
      "motivation": "supplementing",
      "body": {
        "type": "TextualBody",
        "value": "Ky tant esti bias en sa ꝑsone",
        "format": "text/plain"
      },
      "target": {
        "source": "https://digitalcollections.universiteitleiden.nl/iiif_manifest/item:1604565/canvas/default",
        "selector": {
          "type": "FragmentSelector",
          "value": "xywh=3056,1638,821,90"
        }
      }
    },
    {
      "id": "https://digitalcollections.universiteitleiden.nl/iiif_manifest/item:1604565/canvas/default#anno-109",
      "type": "Annotation",
      "motivation": "supplementing",
      "body": {
        "type": "TextualBody",
        "value": "saĩs lymõs. Ky uẽgnẽt/ a la courts",
        "format": "text/plain"
      },
      "target": {
        "source": "https://digitalcollections.universiteitleiden.nl/iiif_manifest/item:1604565/canvas/default",
        "selector": {
          "type": "FragmentSelector",
          "value": "xywh=4053,1600,928,117"
        }
      }
    },
    {
      "id": "https://digitalcollections.universiteitleiden.nl/iiif_manifest/item:1604565/canvas/default#anno-110",
      "type": "Annotation",
      "motivation": "supplementing",
      "body": {
        "type": "TextualBody",
        "value": "Prẽt les eskilhet et les sone",
        "format": "text/plain"
      },
      "target": {
        "source": "https://digitalcollections.universiteitleiden.nl/iiif_manifest/item:1604565/canvas/default",
        "selector": {
          "type": "FragmentSelector",
          "value": "xywh=3067,1698,790,100"
        }
      }
    },
    {
      "id": "https://digitalcollections.universiteitleiden.nl/iiif_manifest/item:1604565/canvas/default#anno-111",
      "type": "Annotation",
      "motivation": "supplementing",
      "body": {
        "type": "TextualBody",
        "value": "Ih̾s. Ay apostele onti respõduti.",
        "format": "text/plain"
      },
      "target": {
        "source": "https://digitalcollections.universiteitleiden.nl/iiif_manifest/item:1604565/canvas/default",
        "selector": {
          "type": "FragmentSelector",
          "value": "xywh=4034,1679,863,121"
        }
      }
    },
    {
      "id": "https://digitalcollections.universiteitleiden.nl/iiif_manifest/item:1604565/canvas/default#anno-112",
      "type": "Annotation",
      "motivation": "supplementing",
      "body": {
        "type": "TextualBody",
        "value": "Puis li at dit a uois lerie.",
        "format": "text/plain"
      },
      "target": {
        "source": "https://digitalcollections.universiteitleiden.nl/iiif_manifest/item:1604565/canvas/default",
        "selector": {
          "type": "FragmentSelector",
          "value": "xywh=3060,1775,755,93"
        }
      }
    },
    {
      "id": "https://digitalcollections.universiteitleiden.nl/iiif_manifest/item:1604565/canvas/default#anno-113",
      "type": "Annotation",
      "motivation": "supplementing",
      "body": {
        "type": "TextualBody",
        "value": "Bñ puit uenire la ꝯpaĩgnie",
        "format": "text/plain"
      },
      "target": {
        "source": "https://digitalcollections.universiteitleiden.nl/iiif_manifest/item:1604565/canvas/default",
        "selector": {
          "type": "FragmentSelector",
          "value": "xywh=3058,1845,806,96"
        }
      }
    },
    {
      "id": "https://digitalcollections.universiteitleiden.nl/iiif_manifest/item:1604565/canvas/default#anno-114",
      "type": "Annotation",
      "motivation": "supplementing",
      "body": {
        "type": "TextualBody",
        "value": "Nos yrõs ciertainemẽt. Dieu en",
        "format": "text/plain"
      },
      "target": {
        "source": "https://digitalcollections.universiteitleiden.nl/iiif_manifest/item:1604565/canvas/default",
        "selector": {
          "type": "FragmentSelector",
          "value": "xywh=3996,1753,953,118"
        }
      }
    },
    {
      "id": "https://digitalcollections.universiteitleiden.nl/iiif_manifest/item:1604565/canvas/default#anno-115",
      "type": "Annotation",
      "motivation": "supplementing",
      "body": {
        "type": "TextualBody",
        "value": "aorrons bõnemet. ¶Etẜ symõs",
        "format": "text/plain"
      },
      "target": {
        "source": "https://digitalcollections.universiteitleiden.nl/iiif_manifest/item:1604565/canvas/default",
        "selector": {
          "type": "FragmentSelector",
          "value": "xywh=4051,1819,910,111"
        }
      }
    },
    {
      "id": "https://digitalcollections.universiteitleiden.nl/iiif_manifest/item:1604565/canvas/default#anno-116",
      "type": "Annotation",
      "motivation": "supplementing",
      "body": {
        "type": "TextualBody",
        "value": "Saĩs gab̾ͥ el at respõdut. Que",
        "format": "text/plain"
      },
      "target": {
        "source": "https://digitalcollections.universiteitleiden.nl/iiif_manifest/item:1604565/canvas/default",
        "selector": {
          "type": "FragmentSelector",
          "value": "xywh=3052,1911,833,102"
        }
      }
    },
    {
      "id": "https://digitalcollections.universiteitleiden.nl/iiif_manifest/item:1604565/canvas/default#anno-117",
      "type": "Annotation",
      "motivation": "supplementing",
      "body": {
        "type": "TextualBody",
        "value": "puis le tournat. Quie plꝰ ne",
        "format": "text/plain"
      },
      "target": {
        "source": "https://digitalcollections.universiteitleiden.nl/iiif_manifest/item:1604565/canvas/default",
        "selector": {
          "type": "FragmentSelector",
          "value": "xywh=4045,1900,833,92"
        }
      }
    },
    {
      "id": "https://digitalcollections.universiteitleiden.nl/iiif_manifest/item:1604565/canvas/default#anno-118",
      "type": "Annotation",
      "motivation": "supplementing",
      "body": {
        "type": "TextualBody",
        "value": "Quãt. les mos ati entẽdut",
        "format": "text/plain"
      },
      "target": {
        "source": "https://digitalcollections.universiteitleiden.nl/iiif_manifest/item:1604565/canvas/default",
        "selector": {
          "type": "FragmentSelector",
          "value": "xywh=3075,1977,791,98"
        }
      }
    },
    {
      "id": "https://digitalcollections.universiteitleiden.nl/iiif_manifest/item:1604565/canvas/default#anno-119",
      "type": "Annotation",
      "motivation": "supplementing",
      "body": {
        "type": "TextualBody",
        "value": "maĩs ny arestat. Car mult est",
        "format": "text/plain"
      },
      "target": {
        "source": "https://digitalcollections.universiteitleiden.nl/iiif_manifest/item:1604565/canvas/default",
        "selector": {
          "type": "FragmentSelector",
          "value": "xywh=4034,1952,910,115"
        }
      }
    },
    {
      "id": "https://digitalcollections.universiteitleiden.nl/iiif_manifest/item:1604565/canvas/default#anno-120",
      "type": "Annotation",
      "motivation": "supplementing",
      "body": {
        "type": "TextualBody",
        "value": "Re plꝰ ne se uoult aresteir/",
        "format": "text/plain"
      },
      "target": {
        "source": "https://digitalcollections.universiteitleiden.nl/iiif_manifest/item:1604565/canvas/default",
        "selector": {
          "type": "FragmentSelector",
          "value": "xywh=3054,2054,793,87"
        }
      }
    },
    {
      "id": "https://digitalcollections.universiteitleiden.nl/iiif_manifest/item:1604565/canvas/default#anno-121",
      "type": "Annotation",
      "motivation": "supplementing",
      "body": {
        "type": "TextualBody",
        "value": "uailhãs cẽlier/. Deuãt ly uoit.",
        "format": "text/plain"
      },
      "target": {
        "source": "https://digitalcollections.universiteitleiden.nl/iiif_manifest/item:1604565/canvas/default",
        "selector": {
          "type": "FragmentSelector",
          "value": "xywh=4028,2016,880,110"
        }
      }
    },
    {
      "id": "https://digitalcollections.universiteitleiden.nl/iiif_manifest/item:1604565/canvas/default#anno-122",
      "type": "Annotation",
      "motivation": "supplementing",
      "body": {
        "type": "TextualBody",
        "value": "Simõ bñ puillies uꝰ uenire",
        "format": "text/plain"
      },
      "target": {
        "source": "https://digitalcollections.universiteitleiden.nl/iiif_manifest/item:1604565/canvas/default",
        "selector": {
          "type": "FragmentSelector",
          "value": "xywh=3054,2118,812,102"
        }
      }
    },
    {
      "id": "https://digitalcollections.universiteitleiden.nl/iiif_manifest/item:1604565/canvas/default#anno-123",
      "type": "Annotation",
      "motivation": "supplementing",
      "body": {
        "type": "TextualBody",
        "value": "les ẜ martire. Qui p̾. dieu furẽt",
        "format": "text/plain"
      },
      "target": {
        "source": "https://digitalcollections.universiteitleiden.nl/iiif_manifest/item:1604565/canvas/default",
        "selector": {
          "type": "FragmentSelector",
          "value": "xywh=4049,2088,874,104"
        }
      }
    },
    {
      "id": "https://digitalcollections.universiteitleiden.nl/iiif_manifest/item:1604565/canvas/default#anno-124",
      "type": "Annotation",
      "motivation": "supplementing",
      "body": {
        "type": "TextualBody",
        "value": "Dit ce q̃ uꝰ aueis a dire. salt̾",
        "format": "text/plain"
      },
      "target": {
        "source": "https://digitalcollections.universiteitleiden.nl/iiif_manifest/item:1604565/canvas/default",
        "selector": {
          "type": "FragmentSelector",
          "value": "xywh=3069,2188,786,92"
        }
      }
    },
    {
      "id": "https://digitalcollections.universiteitleiden.nl/iiif_manifest/item:1604565/canvas/default#anno-125",
      "type": "Annotation",
      "motivation": "supplementing",
      "body": {
        "type": "TextualBody",
        "value": "trauilhies. Saĩs lymons le᷑. dist",
        "format": "text/plain"
      },
      "target": {
        "source": "https://digitalcollections.universiteitleiden.nl/iiif_manifest/item:1604565/canvas/default",
        "selector": {
          "type": "FragmentSelector",
          "value": "xywh=4049,2143,921,118"
        }
      }
    },
    {
      "id": "https://digitalcollections.universiteitleiden.nl/iiif_manifest/item:1604565/canvas/default#anno-126",
      "type": "Annotation",
      "motivation": "supplementing",
      "body": {
        "type": "TextualBody",
        "value": "tost le uꝰ diray bias sire. Me",
        "format": "text/plain"
      },
      "target": {
        "source": "https://digitalcollections.universiteitleiden.nl/iiif_manifest/item:1604565/canvas/default",
        "selector": {
          "type": "FragmentSelector",
          "value": "xywh=3077,2258,797,92"
        }
      }
    },
    {
      "id": "https://digitalcollections.universiteitleiden.nl/iiif_manifest/item:1604565/canvas/default#anno-127",
      "type": "Annotation",
      "motivation": "supplementing",
      "body": {
        "type": "TextualBody",
        "value": "de cuersliet. Bñ puit uenire",
        "format": "text/plain"
      },
      "target": {
        "source": "https://digitalcollections.universiteitleiden.nl/iiif_manifest/item:1604565/canvas/default",
        "selector": {
          "type": "FragmentSelector",
          "value": "xywh=4053,2212,847,119"
        }
      }
    },
    {
      "id": "https://digitalcollections.universiteitleiden.nl/iiif_manifest/item:1604565/canvas/default#anno-128",
      "type": "Annotation",
      "motivation": "supplementing",
      "body": {
        "type": "TextualBody",
        "value": "dist ẜ simõs die uꝰ mãde",
        "format": "text/plain"
      },
      "target": {
        "source": "https://digitalcollections.universiteitleiden.nl/iiif_manifest/item:1604565/canvas/default",
        "selector": {
          "type": "FragmentSelector",
          "value": "xywh=3075,2325,767,93"
        }
      }
    },
    {
      "id": "https://digitalcollections.universiteitleiden.nl/iiif_manifest/item:1604565/canvas/default#anno-129",
      "type": "Annotation",
      "motivation": "supplementing",
      "body": {
        "type": "TextualBody",
        "value": "la ꝯpaĩgnie. Chis qͥ reuiẽt de",
        "format": "text/plain"
      },
      "target": {
        "source": "https://digitalcollections.universiteitleiden.nl/iiif_manifest/item:1604565/canvas/default",
        "selector": {
          "type": "FragmentSelector",
          "value": "xywh=4049,2271,887,139"
        }
      }
    },
    {
      "id": "https://digitalcollections.universiteitleiden.nl/iiif_manifest/item:1604565/canvas/default#anno-130",
      "type": "Annotation",
      "motivation": "supplementing",
      "body": {
        "type": "TextualBody",
        "value": "Et ꝑnꝰ .ii. le uꝰ ꝯmãde. Ilh",
        "format": "text/plain"
      },
      "target": {
        "source": "https://digitalcollections.universiteitleiden.nl/iiif_manifest/item:1604565/canvas/default",
        "selector": {
          "type": "FragmentSelector",
          "value": "xywh=3081,2386,759,107"
        }
      }
    },
    {
      "id": "https://digitalcollections.universiteitleiden.nl/iiif_manifest/item:1604565/canvas/default#anno-131",
      "type": "Annotation",
      "motivation": "supplementing",
      "body": {
        "type": "TextualBody",
        "value": "mort a uie. Beult q̃ uꝰ uẽĩgnies",
        "format": "text/plain"
      },
      "target": {
        "source": "https://digitalcollections.universiteitleiden.nl/iiif_manifest/item:1604565/canvas/default",
        "selector": {
          "type": "FragmentSelector",
          "value": "xywh=4038,2346,938,134"
        }
      }
    },
    {
      "id": "https://digitalcollections.universiteitleiden.nl/iiif_manifest/item:1604565/canvas/default#anno-132",
      "type": "Annotation",
      "motivation": "supplementing",
      "body": {
        "type": "TextualBody",
        "value": "uorat tenire sa court grãde",
        "format": "text/plain"
      },
      "target": {
        "source": "https://digitalcollections.universiteitleiden.nl/iiif_manifest/item:1604565/canvas/default",
        "selector": {
          "type": "FragmentSelector",
          "value": "xywh=3081,2467,813,90"
        }
      }
    },
    {
      "id": "https://digitalcollections.universiteitleiden.nl/iiif_manifest/item:1604565/canvas/default#anno-133",
      "type": "Annotation",
      "motivation": "supplementing",
      "body": {
        "type": "TextualBody",
        "value": "a la court. Ou la fontaine da",
        "format": "text/plain"
      },
      "target": {
        "source": "https://digitalcollections.universiteitleiden.nl/iiif_manifest/item:1604565/canvas/default",
        "selector": {
          "type": "FragmentSelector",
          "value": "xywh=4045,2425,876,113"
        }
      }
    },
    {
      "id": "https://digitalcollections.universiteitleiden.nl/iiif_manifest/item:1604565/canvas/default#anno-134",
      "type": "Annotation",
      "motivation": "supplementing",
      "body": {
        "type": "TextualBody",
        "value": "Or soiies de uenire en grãde",
        "format": "text/plain"
      },
      "target": {
        "source": "https://digitalcollections.universiteitleiden.nl/iiif_manifest/item:1604565/canvas/default",
        "selector": {
          "type": "FragmentSelector",
          "value": "xywh=3079,2527,789,100"
        }
      }
    },
    {
      "id": "https://digitalcollections.universiteitleiden.nl/iiif_manifest/item:1604565/canvas/default#anno-135",
      "type": "Annotation",
      "motivation": "supplementing",
      "body": {
        "type": "TextualBody",
        "value": "mo᷑. court. Car tenire le ueulti",
        "format": "text/plain"
      },
      "target": {
        "source": "https://digitalcollections.universiteitleiden.nl/iiif_manifest/item:1604565/canvas/default",
        "selector": {
          "type": "FragmentSelector",
          "value": "xywh=4034,2487,927,127"
        }
      }
    },
    {
      "id": "https://digitalcollections.universiteitleiden.nl/iiif_manifest/item:1604565/canvas/default#anno-136",
      "type": "Annotation",
      "motivation": "supplementing",
      "body": {
        "type": "TextualBody",
        "value": "Et lamineis uꝰ ꝯpaĩgnie.",
        "format": "text/plain"
      },
      "target": {
        "source": "https://digitalcollections.universiteitleiden.nl/iiif_manifest/item:1604565/canvas/default",
        "selector": {
          "type": "FragmentSelector",
          "value": "xywh=3084,2599,731,98"
        }
      }
    },
    {
      "id": "https://digitalcollections.universiteitleiden.nl/iiif_manifest/item:1604565/canvas/default#anno-137",
      "type": "Annotation",
      "motivation": "supplementing",
      "body": {
        "type": "TextualBody",
        "value": "haute et grãde. Saĩs estieune",
        "format": "text/plain"
      },
      "target": {
        "source": "https://digitalcollections.universiteitleiden.nl/iiif_manifest/item:1604565/canvas/default",
        "selector": {
          "type": "FragmentSelector",
          "value": "xywh=4049,2567,910,105"
        }
      }
    },
    {
      "id": "https://digitalcollections.universiteitleiden.nl/iiif_manifest/item:1604565/canvas/default#anno-138",
      "type": "Annotation",
      "motivation": "supplementing",
      "body": {
        "type": "TextualBody",
        "value": "Gardeis q̃ muls ny remaint",
        "format": "text/plain"
      },
      "target": {
        "source": "https://digitalcollections.universiteitleiden.nl/iiif_manifest/item:1604565/canvas/default",
        "selector": {
          "type": "FragmentSelector",
          "value": "xywh=3081,2668,806,79"
        }
      }
    },
    {
      "id": "https://digitalcollections.universiteitleiden.nl/iiif_manifest/item:1604565/canvas/default#anno-139",
      "type": "Annotation",
      "motivation": "supplementing",
      "body": {
        "type": "TextualBody",
        "value": "a hault alaine. Ly respõdit",
        "format": "text/plain"
      },
      "target": {
        "source": "https://digitalcollections.universiteitleiden.nl/iiif_manifest/item:1604565/canvas/default",
        "selector": {
          "type": "FragmentSelector",
          "value": "xywh=4045,2640,842,111"
        }
      }
    },
    {
      "id": "https://digitalcollections.universiteitleiden.nl/iiif_manifest/item:1604565/canvas/default#anno-140",
      "type": "Annotation",
      "motivation": "supplementing",
      "body": {
        "type": "TextualBody",
        "value": "niẽt . Saĩs gabͥel hi respõ-",
        "format": "text/plain"
      },
      "target": {
        "source": "https://digitalcollections.universiteitleiden.nl/iiif_manifest/item:1604565/canvas/default",
        "selector": {
          "type": "FragmentSelector",
          "value": "xywh=3094,2727,772,103"
        }
      }
    },
    {
      "id": "https://digitalcollections.universiteitleiden.nl/iiif_manifest/item:1604565/canvas/default#anno-141",
      "type": "Annotation",
      "motivation": "supplementing",
      "body": {
        "type": "TextualBody",
        "value": "dit Ke plꝰ ne moĩs ny atẽ-",
        "format": "text/plain"
      },
      "target": {
        "source": "https://digitalcollections.universiteitleiden.nl/iiif_manifest/item:1604565/canvas/default",
        "selector": {
          "type": "FragmentSelector",
          "value": "xywh=3090,2791,787,105"
        }
      }
    },
    {
      "id": "https://digitalcollections.universiteitleiden.nl/iiif_manifest/item:1604565/canvas/default#anno-142",
      "type": "Annotation",
      "motivation": "supplementing",
      "body": {
        "type": "TextualBody",
        "value": "nꝰ lotͥono. Sachies uolẽtire nꝰ",
        "format": "text/plain"
      },
      "target": {
        "source": "https://digitalcollections.universiteitleiden.nl/iiif_manifest/item:1604565/canvas/default",
        "selector": {
          "type": "FragmentSelector",
          "value": "xywh=4036,2710,900,111"
        }
      }
    },
    {
      "id": "https://digitalcollections.universiteitleiden.nl/iiif_manifest/item:1604565/canvas/default#anno-143",
      "type": "Annotation",
      "motivation": "supplementing",
      "body": {
        "type": "TextualBody",
        "value": "dit Simõs fuit il nꝰ lotͥons.",
        "format": "text/plain"
      },
      "target": {
        "source": "https://digitalcollections.universiteitleiden.nl/iiif_manifest/item:1604565/canvas/default",
        "selector": {
          "type": "FragmentSelector",
          "value": "xywh=3092,2862,821,130"
        }
      }
    },
    {
      "id": "https://digitalcollections.universiteitleiden.nl/iiif_manifest/item:1604565/canvas/default#anno-144",
      "type": "Annotation",
      "motivation": "supplementing",
      "body": {
        "type": "TextualBody",
        "value": "yrõs. Ia uns seule ny remã-",
        "format": "text/plain"
      },
      "target": {
        "source": "https://digitalcollections.universiteitleiden.nl/iiif_manifest/item:1604565/canvas/default",
        "selector": {
          "type": "FragmentSelector",
          "value": "xywh=4032,2781,900,115"
        }
      }
    },
    {
      "id": "https://digitalcollections.universiteitleiden.nl/iiif_manifest/item:1604565/canvas/default#anno-145",
      "type": "Annotation",
      "motivation": "supplementing",
      "body": {
        "type": "TextualBody",
        "value": "rat. Et ẜ lymõ puis sen tour-",
        "format": "text/plain"
      },
      "target": {
        "source": "https://digitalcollections.universiteitleiden.nl/iiif_manifest/item:1604565/canvas/default",
        "selector": {
          "type": "FragmentSelector",
          "value": "xywh=4024,2855,910,126"
        }
      }
    },
    {
      "id": "https://digitalcollections.universiteitleiden.nl/iiif_manifest/item:1604565/canvas/default#anno-146",
      "type": "Annotation",
      "motivation": "supplementing",
      "body": {
        "type": "TextualBody",
        "value": "¶",
        "format": "text/plain"
      },
      "target": {
        "source": "https://digitalcollections.universiteitleiden.nl/iiif_manifest/item:1604565/canvas/default",
        "selector": {
          "type": "FragmentSelector",
          "value": "xywh=3122,2985,47,124"
        }
      }
    },
    {
      "id": "https://digitalcollections.universiteitleiden.nl/iiif_manifest/item:1604565/canvas/default#anno-147",
      "type": "Annotation",
      "motivation": "supplementing",
      "body": {
        "type": "TextualBody",
        "value": "Cu",
        "format": "text/plain"
      },
      "target": {
        "source": "https://digitalcollections.universiteitleiden.nl/iiif_manifest/item:1604565/canvas/default",
        "selector": {
          "type": "FragmentSelector",
          "value": "xywh=3361,3183,115,77"
        }
      }
    },
    {
      "id": "https://digitalcollections.universiteitleiden.nl/iiif_manifest/item:1604565/canvas/default#anno-148",
      "type": "Annotation",
      "motivation": "supplementing",
      "body": {
        "type": "TextualBody",
        "value": "1",
        "format": "text/plain"
      },
      "target": {
        "source": "https://digitalcollections.universiteitleiden.nl/iiif_manifest/item:1604565/canvas/default",
        "selector": {
          "type": "FragmentSelector",
          "value": "xywh=5160,432,64,134"
        }
      }
    },
    {
      "id": "https://digitalcollections.universiteitleiden.nl/iiif_manifest/item:1604565/canvas/default#anno-149",
      "type": "Annotation",
      "motivation": "supplementing",
      "body": {
        "type": "TextualBody",
        "value": "6u",
        "format": "text/plain"
      },
      "target": {
        "source": "https://digitalcollections.universiteitleiden.nl/iiif_manifest/item:1604565/canvas/default",
        "selector": {
          "type": "FragmentSelector",
          "value": "xywh=4241,3211,119,75"
        }
      }
    },
    {
      "id": "https://digitalcollections.universiteitleiden.nl/iiif_manifest/item:1604565/canvas/default#anno-150",
      "type": "Annotation",
      "motivation": "supplementing",
      "body": {
        "type": "TextualBody",
        "value": "bit",
        "format": "text/plain"
      },
      "target": {
        "source": "https://digitalcollections.universiteitleiden.nl/iiif_manifest/item:1604565/canvas/default",
        "selector": {
          "type": "FragmentSelector",
          "value": "xywh=4582,3190,109,96"
        }
      }
    }
  ]
}