{
  "id": "data/annos/clm-22016/p161.ap.json",
  "type": "AnnotationPage",
  "items": [
    {
      "id": "https://api.digitale-sammlungen.de/iiif/presentation/v2/bsb00034225/canvas/161#anno-1",
      "type": "Annotation",
      "motivation": "supplementing",
      "body": {
        "type": "TextualBody",
        "value": "torquet᷑ incuiꝰ extremo incarnatꝰ",
        "format": "text/plain"
      },
      "target": {
        "source": "https://api.digitale-sammlungen.de/iiif/presentation/v2/bsb00034225/canvas/161",
        "selector": {
          "type": "FragmentSelector",
          "value": "xywh=142,215,826,89"
        }
      }
    },
    {
      "id": "https://api.digitale-sammlungen.de/iiif/presentation/v2/bsb00034225/canvas/161#anno-2",
      "type": "Annotation",
      "motivation": "supplementing",
      "body": {
        "type": "TextualBody",
        "value": "dñs id est hamus iste ligaret᷑. quẽ",
        "format": "text/plain"
      },
      "target": {
        "source": "https://api.digitale-sammlungen.de/iiif/presentation/v2/bsb00034225/canvas/161",
        "selector": {
          "type": "FragmentSelector",
          "value": "xywh=147,274,846,105"
        }
      }
    },
    {
      "id": "https://api.digitale-sammlungen.de/iiif/presentation/v2/bsb00034225/canvas/161#anno-3",
      "type": "Annotation",
      "motivation": "supplementing",
      "body": {
        "type": "TextualBody",
        "value": "simus adã id ẽ axpc̃ in spm̃ uuu",
        "format": "text/plain"
      },
      "target": {
        "source": "https://api.digitale-sammlungen.de/iiif/presentation/v2/bsb00034225/canvas/161",
        "selector": {
          "type": "FragmentSelector",
          "value": "xywh=1117,238,825,103"
        }
      }
    },
    {
      "id": "https://api.digitale-sammlungen.de/iiif/presentation/v2/bsb00034225/canvas/161#anno-4",
      "type": "Annotation",
      "motivation": "supplementing",
      "body": {
        "type": "TextualBody",
        "value": "in his aquis humani generis de",
        "format": "text/plain"
      },
      "target": {
        "source": "https://api.digitale-sammlungen.de/iiif/presentation/v2/bsb00034225/canvas/161",
        "selector": {
          "type": "FragmentSelector",
          "value": "xywh=140,345,791,102"
        }
      }
    },
    {
      "id": "https://api.digitale-sammlungen.de/iiif/presentation/v2/bsb00034225/canvas/161#anno-5",
      "type": "Annotation",
      "motivation": "supplementing",
      "body": {
        "type": "TextualBody",
        "value": "ficantem. In allo om̃s moriunt᷑.",
        "format": "text/plain"
      },
      "target": {
        "source": "https://api.digitale-sammlungen.de/iiif/presentation/v2/bsb00034225/canvas/161",
        "selector": {
          "type": "FragmentSelector",
          "value": "xywh=1113,306,844,109"
        }
      }
    },
    {
      "id": "https://api.digitale-sammlungen.de/iiif/presentation/v2/bsb00034225/canvas/161#anno-6",
      "type": "Annotation",
      "motivation": "supplementing",
      "body": {
        "type": "TextualBody",
        "value": "pendentẽ aperto ore cętus iste",
        "format": "text/plain"
      },
      "target": {
        "source": "https://api.digitale-sammlungen.de/iiif/presentation/v2/bsb00034225/canvas/161",
        "selector": {
          "type": "FragmentSelector",
          "value": "xywh=140,424,791,98"
        }
      }
    },
    {
      "id": "https://api.digitale-sammlungen.de/iiif/presentation/v2/bsb00034225/canvas/161#anno-7",
      "type": "Annotation",
      "motivation": "supplementing",
      "body": {
        "type": "TextualBody",
        "value": "inisto om̃s uuuficant᷑. Quando",
        "format": "text/plain"
      },
      "target": {
        "source": "https://api.digitale-sammlungen.de/iiif/presentation/v2/bsb00034225/canvas/161",
        "selector": {
          "type": "FragmentSelector",
          "value": "xywh=1110,377,804,109"
        }
      }
    },
    {
      "id": "https://api.digitale-sammlungen.de/iiif/presentation/v2/bsb00034225/canvas/161#anno-8",
      "type": "Annotation",
      "motivation": "supplementing",
      "body": {
        "type": "TextualBody",
        "value": "uel leuiathan appeteret. sed eo ꝑ",
        "format": "text/plain"
      },
      "target": {
        "source": "https://api.digitale-sammlungen.de/iiif/presentation/v2/bsb00034225/canvas/161",
        "selector": {
          "type": "FragmentSelector",
          "value": "xywh=136,500,812,96"
        }
      }
    },
    {
      "id": "https://api.digitale-sammlungen.de/iiif/presentation/v2/bsb00034225/canvas/161#anno-9",
      "type": "Annotation",
      "motivation": "supplementing",
      "body": {
        "type": "TextualBody",
        "value": "portamꝰ imaginẽ terreni. homi",
        "format": "text/plain"
      },
      "target": {
        "source": "https://api.digitale-sammlungen.de/iiif/presentation/v2/bsb00034225/canvas/161",
        "selector": {
          "type": "FragmentSelector",
          "value": "xywh=1108,456,806,96"
        }
      }
    },
    {
      "id": "https://api.digitale-sammlungen.de/iiif/presentation/v2/bsb00034225/canvas/161#anno-10",
      "type": "Annotation",
      "motivation": "supplementing",
      "body": {
        "type": "TextualBody",
        "value": "satellitũ. suorũ scustiã morsu mor",
        "format": "text/plain"
      },
      "target": {
        "source": "https://api.digitale-sammlungen.de/iiif/presentation/v2/bsb00034225/canvas/161",
        "selector": {
          "type": "FragmentSelector",
          "value": "xywh=134,569,853,106"
        }
      }
    },
    {
      "id": "https://api.digitale-sammlungen.de/iiif/presentation/v2/bsb00034225/canvas/161#anno-11",
      "type": "Annotation",
      "motivation": "supplementing",
      "body": {
        "type": "TextualBody",
        "value": "nes sumus. quando portamꝰ ima",
        "format": "text/plain"
      },
      "target": {
        "source": "https://api.digitale-sammlungen.de/iiif/presentation/v2/bsb00034225/canvas/161",
        "selector": {
          "type": "FragmentSelector",
          "value": "xywh=1108,522,830,102"
        }
      }
    },
    {
      "id": "https://api.digitale-sammlungen.de/iiif/presentation/v2/bsb00034225/canvas/161#anno-12",
      "type": "Annotation",
      "motivation": "supplementing",
      "body": {
        "type": "TextualBody",
        "value": "dendi uires ulteri non haberet.",
        "format": "text/plain"
      },
      "target": {
        "source": "https://api.digitale-sammlungen.de/iiif/presentation/v2/bsb00034225/canvas/161",
        "selector": {
          "type": "FragmentSelector",
          "value": "xywh=134,656,808,96"
        }
      }
    },
    {
      "id": "https://api.digitale-sammlungen.de/iiif/presentation/v2/bsb00034225/canvas/161#anno-13",
      "type": "Annotation",
      "motivation": "supplementing",
      "body": {
        "type": "TextualBody",
        "value": "ginẽ cęlestis hominis. filu. ho",
        "format": "text/plain"
      },
      "target": {
        "source": "https://api.digitale-sammlungen.de/iiif/presentation/v2/bsb00034225/canvas/161",
        "selector": {
          "type": "FragmentSelector",
          "value": "xywh=1106,598,791,107"
        }
      }
    },
    {
      "id": "https://api.digitale-sammlungen.de/iiif/presentation/v2/bsb00034225/canvas/161#anno-14",
      "type": "Annotation",
      "motivation": "supplementing",
      "body": {
        "type": "TextualBody",
        "value": "et hamus hic id ẽ incarnatio dĩ",
        "format": "text/plain"
      },
      "target": {
        "source": "https://api.digitale-sammlungen.de/iiif/presentation/v2/bsb00034225/canvas/161",
        "selector": {
          "type": "FragmentSelector",
          "value": "xywh=132,718,810,96"
        }
      }
    },
    {
      "id": "https://api.digitale-sammlungen.de/iiif/presentation/v2/bsb00034225/canvas/161#anno-15",
      "type": "Annotation",
      "motivation": "supplementing",
      "body": {
        "type": "TextualBody",
        "value": "minũ sumus. qͥa xpc filiꝰ hominis",
        "format": "text/plain"
      },
      "target": {
        "source": "https://api.digitale-sammlungen.de/iiif/presentation/v2/bsb00034225/canvas/161",
        "selector": {
          "type": "FragmentSelector",
          "value": "xywh=1104,671,876,113"
        }
      }
    },
    {
      "id": "https://api.digitale-sammlungen.de/iiif/presentation/v2/bsb00034225/canvas/161#anno-16",
      "type": "Annotation",
      "motivation": "supplementing",
      "body": {
        "type": "TextualBody",
        "value": "& hominis fauces raptoris tenu",
        "format": "text/plain"
      },
      "target": {
        "source": "https://api.digitale-sammlungen.de/iiif/presentation/v2/bsb00034225/canvas/161",
        "selector": {
          "type": "FragmentSelector",
          "value": "xywh=127,788,834,107"
        }
      }
    },
    {
      "id": "https://api.digitale-sammlungen.de/iiif/presentation/v2/bsb00034225/canvas/161#anno-17",
      "type": "Annotation",
      "motivation": "supplementing",
      "body": {
        "type": "TextualBody",
        "value": "dictus ẽ. ꝑada exterior &uetꝰ",
        "format": "text/plain"
      },
      "target": {
        "source": "https://api.digitale-sammlungen.de/iiif/presentation/v2/bsb00034225/canvas/161",
        "selector": {
          "type": "FragmentSelector",
          "value": "xywh=1104,748,834,106"
        }
      }
    },
    {
      "id": "https://api.digitale-sammlungen.de/iiif/presentation/v2/bsb00034225/canvas/161#anno-18",
      "type": "Annotation",
      "motivation": "supplementing",
      "body": {
        "type": "TextualBody",
        "value": "it & sese mordentẽ momordit.",
        "format": "text/plain"
      },
      "target": {
        "source": "https://api.digitale-sammlungen.de/iiif/presentation/v2/bsb00034225/canvas/161",
        "selector": {
          "type": "FragmentSelector",
          "value": "xywh=127,865,802,100"
        }
      }
    },
    {
      "id": "https://api.digitale-sammlungen.de/iiif/presentation/v2/bsb00034225/canvas/161#anno-19",
      "type": "Annotation",
      "motivation": "supplementing",
      "body": {
        "type": "TextualBody",
        "value": "homo nr̃ corrumpit᷑. pa p̃m",
        "format": "text/plain"
      },
      "target": {
        "source": "https://api.digitale-sammlungen.de/iiif/presentation/v2/bsb00034225/canvas/161",
        "selector": {
          "type": "FragmentSelector",
          "value": "xywh=1100,818,789,105"
        }
      }
    },
    {
      "id": "https://api.digitale-sammlungen.de/iiif/presentation/v2/bsb00034225/canvas/161#anno-20",
      "type": "Annotation",
      "motivation": "supplementing",
      "body": {
        "type": "TextualBody",
        "value": "Ds̃ est pat̾ & filius et spe sc̃s.ꝑ",
        "format": "text/plain"
      },
      "target": {
        "source": "https://api.digitale-sammlungen.de/iiif/presentation/v2/bsb00034225/canvas/161",
        "selector": {
          "type": "FragmentSelector",
          "value": "xywh=115,925,827,119"
        }
      }
    },
    {
      "id": "https://api.digitale-sammlungen.de/iiif/presentation/v2/bsb00034225/canvas/161#anno-21",
      "type": "Annotation",
      "motivation": "supplementing",
      "body": {
        "type": "TextualBody",
        "value": "interior dedie indiẽ renouat᷑.",
        "format": "text/plain"
      },
      "target": {
        "source": "https://api.digitale-sammlungen.de/iiif/presentation/v2/bsb00034225/canvas/161",
        "selector": {
          "type": "FragmentSelector",
          "value": "xywh=1100,895,840,102"
        }
      }
    },
    {
      "id": "https://api.digitale-sammlungen.de/iiif/presentation/v2/bsb00034225/canvas/161#anno-22",
      "type": "Annotation",
      "motivation": "supplementing",
      "body": {
        "type": "TextualBody",
        "value": "Uetus homo ad peccatũ & in ui",
        "format": "text/plain"
      },
      "target": {
        "source": "https://api.digitale-sammlungen.de/iiif/presentation/v2/bsb00034225/canvas/161",
        "selector": {
          "type": "FragmentSelector",
          "value": "xywh=1100,959,829,108"
        }
      }
    },
    {
      "id": "https://api.digitale-sammlungen.de/iiif/presentation/v2/bsb00034225/canvas/161#anno-23",
      "type": "Annotation",
      "motivation": "supplementing",
      "body": {
        "type": "TextualBody",
        "value": "intrib ꝑsonis unus & cocternus.",
        "format": "text/plain"
      },
      "target": {
        "source": "https://api.digitale-sammlungen.de/iiif/presentation/v2/bsb00034225/canvas/161",
        "selector": {
          "type": "FragmentSelector",
          "value": "xywh=130,1014,846,105"
        }
      }
    },
    {
      "id": "https://api.digitale-sammlungen.de/iiif/presentation/v2/bsb00034225/canvas/161#anno-24",
      "type": "Annotation",
      "motivation": "supplementing",
      "body": {
        "type": "TextualBody",
        "value": "Homo inscã scriptura trib: mo",
        "format": "text/plain"
      },
      "target": {
        "source": "https://api.digitale-sammlungen.de/iiif/presentation/v2/bsb00034225/canvas/161",
        "selector": {
          "type": "FragmentSelector",
          "value": "xywh=89,1076,913,128"
        }
      }
    },
    {
      "id": "https://api.digitale-sammlungen.de/iiif/presentation/v2/bsb00034225/canvas/161#anno-25",
      "type": "Annotation",
      "motivation": "supplementing",
      "body": {
        "type": "TextualBody",
        "value": "stitiã. nouus homo reputat᷑ ad",
        "format": "text/plain"
      },
      "target": {
        "source": "https://api.digitale-sammlungen.de/iiif/presentation/v2/bsb00034225/canvas/161",
        "selector": {
          "type": "FragmentSelector",
          "value": "xywh=1096,1035,827,116"
        }
      }
    },
    {
      "id": "https://api.digitale-sammlungen.de/iiif/presentation/v2/bsb00034225/canvas/161#anno-26",
      "type": "Annotation",
      "motivation": "supplementing",
      "body": {
        "type": "TextualBody",
        "value": "dis dicit᷑. natura. culpa. infirmi",
        "format": "text/plain"
      },
      "target": {
        "source": "https://api.digitale-sammlungen.de/iiif/presentation/v2/bsb00034225/canvas/161",
        "selector": {
          "type": "FragmentSelector",
          "value": "xywh=117,1161,855,103"
        }
      }
    },
    {
      "id": "https://api.digitale-sammlungen.de/iiif/presentation/v2/bsb00034225/canvas/161#anno-27",
      "type": "Annotation",
      "motivation": "supplementing",
      "body": {
        "type": "TextualBody",
        "value": "iustitiã. De homine interiori &",
        "format": "text/plain"
      },
      "target": {
        "source": "https://api.digitale-sammlungen.de/iiif/presentation/v2/bsb00034225/canvas/161",
        "selector": {
          "type": "FragmentSelector",
          "value": "xywh=1093,1112,830,107"
        }
      }
    },
    {
      "id": "https://api.digitale-sammlungen.de/iiif/presentation/v2/bsb00034225/canvas/161#anno-28",
      "type": "Annotation",
      "motivation": "supplementing",
      "body": {
        "type": "TextualBody",
        "value": "tate. Int illã gͦ summã trinita",
        "format": "text/plain"
      },
      "target": {
        "source": "https://api.digitale-sammlungen.de/iiif/presentation/v2/bsb00034225/canvas/161",
        "selector": {
          "type": "FragmentSelector",
          "value": "xywh=113,1244,852,86"
        }
      }
    },
    {
      "id": "https://api.digitale-sammlungen.de/iiif/presentation/v2/bsb00034225/canvas/161#anno-29",
      "type": "Annotation",
      "motivation": "supplementing",
      "body": {
        "type": "TextualBody",
        "value": "Homo gͦ c̃stat eor anima exteriori",
        "format": "text/plain"
      },
      "target": {
        "source": "https://api.digitale-sammlungen.de/iiif/presentation/v2/bsb00034225/canvas/161",
        "selector": {
          "type": "FragmentSelector",
          "value": "xywh=1023,1180,945,126"
        }
      }
    },
    {
      "id": "https://api.digitale-sammlungen.de/iiif/presentation/v2/bsb00034225/canvas/161#anno-30",
      "type": "Annotation",
      "motivation": "supplementing",
      "body": {
        "type": "TextualBody",
        "value": "tem et hominũ infirmitatẽ & in",
        "format": "text/plain"
      },
      "target": {
        "source": "https://api.digitale-sammlungen.de/iiif/presentation/v2/bsb00034225/canvas/161",
        "selector": {
          "type": "FragmentSelector",
          "value": "xywh=108,1304,840,92"
        }
      }
    },
    {
      "id": "https://api.digitale-sammlungen.de/iiif/presentation/v2/bsb00034225/canvas/161#anno-31",
      "type": "Annotation",
      "motivation": "supplementing",
      "body": {
        "type": "TextualBody",
        "value": "& corpore. sed ipsa anima huma",
        "format": "text/plain"
      },
      "target": {
        "source": "https://api.digitale-sammlungen.de/iiif/presentation/v2/bsb00034225/canvas/161",
        "selector": {
          "type": "FragmentSelector",
          "value": "xywh=1096,1266,833,106"
        }
      }
    },
    {
      "id": "https://api.digitale-sammlungen.de/iiif/presentation/v2/bsb00034225/canvas/161#anno-32",
      "type": "Annotation",
      "motivation": "supplementing",
      "body": {
        "type": "TextualBody",
        "value": "iquitatẽ mediator factus ẽ ho",
        "format": "text/plain"
      },
      "target": {
        "source": "https://api.digitale-sammlungen.de/iiif/presentation/v2/bsb00034225/canvas/161",
        "selector": {
          "type": "FragmentSelector",
          "value": "xywh=108,1370,832,105"
        }
      }
    },
    {
      "id": "https://api.digitale-sammlungen.de/iiif/presentation/v2/bsb00034225/canvas/161#anno-33",
      "type": "Annotation",
      "motivation": "supplementing",
      "body": {
        "type": "TextualBody",
        "value": "na habet aliquid qđ ñ habent",
        "format": "text/plain"
      },
      "target": {
        "source": "https://api.digitale-sammlungen.de/iiif/presentation/v2/bsb00034225/canvas/161",
        "selector": {
          "type": "FragmentSelector",
          "value": "xywh=1093,1338,811,107"
        }
      }
    },
    {
      "id": "https://api.digitale-sammlungen.de/iiif/presentation/v2/bsb00034225/canvas/161#anno-34",
      "type": "Annotation",
      "motivation": "supplementing",
      "body": {
        "type": "TextualBody",
        "value": "mo ñ iniquus sed tam̃ infirmus.",
        "format": "text/plain"
      },
      "target": {
        "source": "https://api.digitale-sammlungen.de/iiif/presentation/v2/bsb00034225/canvas/161",
        "selector": {
          "type": "FragmentSelector",
          "value": "xywh=108,1445,843,100"
        }
      }
    },
    {
      "id": "https://api.digitale-sammlungen.de/iiif/presentation/v2/bsb00034225/canvas/161#anno-35",
      "type": "Annotation",
      "motivation": "supplementing",
      "body": {
        "type": "TextualBody",
        "value": "animȩ pecorũ. Nam et pecora",
        "format": "text/plain"
      },
      "target": {
        "source": "https://api.digitale-sammlungen.de/iiif/presentation/v2/bsb00034225/canvas/161",
        "selector": {
          "type": "FragmentSelector",
          "value": "xywh=1089,1409,796,104"
        }
      }
    },
    {
      "id": "https://api.digitale-sammlungen.de/iiif/presentation/v2/bsb00034225/canvas/161#anno-36",
      "type": "Annotation",
      "motivation": "supplementing",
      "body": {
        "type": "TextualBody",
        "value": "ut ex eo quod ñ iniquus iungera",
        "format": "text/plain"
      },
      "target": {
        "source": "https://api.digitale-sammlungen.de/iiif/presentation/v2/bsb00034225/canvas/161",
        "selector": {
          "type": "FragmentSelector",
          "value": "xywh=106,1517,857,109"
        }
      }
    },
    {
      "id": "https://api.digitale-sammlungen.de/iiif/presentation/v2/bsb00034225/canvas/161#anno-37",
      "type": "Annotation",
      "motivation": "supplementing",
      "body": {
        "type": "TextualBody",
        "value": "animã habent & animalia uo",
        "format": "text/plain"
      },
      "target": {
        "source": "https://api.digitale-sammlungen.de/iiif/presentation/v2/bsb00034225/canvas/161",
        "selector": {
          "type": "FragmentSelector",
          "value": "xywh=1085,1487,797,92"
        }
      }
    },
    {
      "id": "https://api.digitale-sammlungen.de/iiif/presentation/v2/bsb00034225/canvas/161#anno-38",
      "type": "Annotation",
      "motivation": "supplementing",
      "body": {
        "type": "TextualBody",
        "value": "te dõ. eeo qđ infirmus ꝓpinqua",
        "format": "text/plain"
      },
      "target": {
        "source": "https://api.digitale-sammlungen.de/iiif/presentation/v2/bsb00034225/canvas/161",
        "selector": {
          "type": "FragmentSelector",
          "value": "xywh=104,1590,859,111"
        }
      }
    },
    {
      "id": "https://api.digitale-sammlungen.de/iiif/presentation/v2/bsb00034225/canvas/161#anno-39",
      "type": "Annotation",
      "motivation": "supplementing",
      "body": {
        "type": "TextualBody",
        "value": "cant᷑. Non enim uocant᷑ anima",
        "format": "text/plain"
      },
      "target": {
        "source": "https://api.digitale-sammlungen.de/iiif/presentation/v2/bsb00034225/canvas/161",
        "selector": {
          "type": "FragmentSelector",
          "value": "xywh=1081,1551,833,107"
        }
      }
    },
    {
      "id": "https://api.digitale-sammlungen.de/iiif/presentation/v2/bsb00034225/canvas/161#anno-40",
      "type": "Annotation",
      "motivation": "supplementing",
      "body": {
        "type": "TextualBody",
        "value": "ret tͥ. atq ita intdm et hominẽ",
        "format": "text/plain"
      },
      "target": {
        "source": "https://api.digitale-sammlungen.de/iiif/presentation/v2/bsb00034225/canvas/161",
        "selector": {
          "type": "FragmentSelector",
          "value": "xywh=102,1664,853,103"
        }
      }
    },
    {
      "id": "https://api.digitale-sammlungen.de/iiif/presentation/v2/bsb00034225/canvas/161#anno-41",
      "type": "Annotation",
      "motivation": "supplementing",
      "body": {
        "type": "TextualBody",
        "value": "lia nisi ab anima. & uidemꝰ qͥa",
        "format": "text/plain"
      },
      "target": {
        "source": "https://api.digitale-sammlungen.de/iiif/presentation/v2/bsb00034225/canvas/161",
        "selector": {
          "type": "FragmentSelector",
          "value": "xywh=1078,1620,847,113"
        }
      }
    },
    {
      "id": "https://api.digitale-sammlungen.de/iiif/presentation/v2/bsb00034225/canvas/161#anno-42",
      "type": "Annotation",
      "motivation": "supplementing",
      "body": {
        "type": "TextualBody",
        "value": "filius di mediator ecisteret.",
        "format": "text/plain"
      },
      "target": {
        "source": "https://api.digitale-sammlungen.de/iiif/presentation/v2/bsb00034225/canvas/161",
        "selector": {
          "type": "FragmentSelector",
          "value": "xywh=106,1743,791,98"
        }
      }
    },
    {
      "id": "https://api.digitale-sammlungen.de/iiif/presentation/v2/bsb00034225/canvas/161#anno-43",
      "type": "Annotation",
      "motivation": "supplementing",
      "body": {
        "type": "TextualBody",
        "value": "& ipsa uiuunt. Sed quid ampliꝰ",
        "format": "text/plain"
      },
      "target": {
        "source": "https://api.digitale-sammlungen.de/iiif/presentation/v2/bsb00034225/canvas/161",
        "selector": {
          "type": "FragmentSelector",
          "value": "xywh=1081,1694,853,117"
        }
      }
    },
    {
      "id": "https://api.digitale-sammlungen.de/iiif/presentation/v2/bsb00034225/canvas/161#anno-44",
      "type": "Annotation",
      "motivation": "supplementing",
      "body": {
        "type": "TextualBody",
        "value": "uerbũ caro factũ ẽ. uerbũ ho",
        "format": "text/plain"
      },
      "target": {
        "source": "https://api.digitale-sammlungen.de/iiif/presentation/v2/bsb00034225/canvas/161",
        "selector": {
          "type": "FragmentSelector",
          "value": "xywh=110,1820,794,100"
        }
      }
    },
    {
      "id": "https://api.digitale-sammlungen.de/iiif/presentation/v2/bsb00034225/canvas/161#anno-45",
      "type": "Annotation",
      "motivation": "supplementing",
      "body": {
        "type": "TextualBody",
        "value": "habet homo. Quia factus ẽ ad",
        "format": "text/plain"
      },
      "target": {
        "source": "https://api.digitale-sammlungen.de/iiif/presentation/v2/bsb00034225/canvas/161",
        "selector": {
          "type": "FragmentSelector",
          "value": "xywh=1078,1773,828,107"
        }
      }
    },
    {
      "id": "https://api.digitale-sammlungen.de/iiif/presentation/v2/bsb00034225/canvas/161#anno-46",
      "type": "Annotation",
      "motivation": "supplementing",
      "body": {
        "type": "TextualBody",
        "value": "mo factus ẽ. Nomine enimcar",
        "format": "text/plain"
      },
      "target": {
        "source": "https://api.digitale-sammlungen.de/iiif/presentation/v2/bsb00034225/canvas/161",
        "selector": {
          "type": "FragmentSelector",
          "value": "xywh=106,1892,819,96"
        }
      }
    },
    {
      "id": "https://api.digitale-sammlungen.de/iiif/presentation/v2/bsb00034225/canvas/161#anno-47",
      "type": "Annotation",
      "motivation": "supplementing",
      "body": {
        "type": "TextualBody",
        "value": "imaginẽ dĩ. unde intelligit &",
        "format": "text/plain"
      },
      "target": {
        "source": "https://api.digitale-sammlungen.de/iiif/presentation/v2/bsb00034225/canvas/161",
        "selector": {
          "type": "FragmentSelector",
          "value": "xywh=1072,1854,827,111"
        }
      }
    },
    {
      "id": "https://api.digitale-sammlungen.de/iiif/presentation/v2/bsb00034225/canvas/161#anno-48",
      "type": "Annotation",
      "motivation": "supplementing",
      "body": {
        "type": "TextualBody",
        "value": "nis appellati s̃ homines. Inde",
        "format": "text/plain"
      },
      "target": {
        "source": "https://api.digitale-sammlungen.de/iiif/presentation/v2/bsb00034225/canvas/161",
        "selector": {
          "type": "FragmentSelector",
          "value": "xywh=102,1967,819,104"
        }
      }
    },
    {
      "id": "https://api.digitale-sammlungen.de/iiif/presentation/v2/bsb00034225/canvas/161#anno-49",
      "type": "Annotation",
      "motivation": "supplementing",
      "body": {
        "type": "TextualBody",
        "value": "sapit. bonũ amalo discernit.",
        "format": "text/plain"
      },
      "target": {
        "source": "https://api.digitale-sammlungen.de/iiif/presentation/v2/bsb00034225/canvas/161",
        "selector": {
          "type": "FragmentSelector",
          "value": "xywh=1074,1924,802,105"
        }
      }
    },
    {
      "id": "https://api.digitale-sammlungen.de/iiif/presentation/v2/bsb00034225/canvas/161#anno-50",
      "type": "Annotation",
      "motivation": "supplementing",
      "body": {
        "type": "TextualBody",
        "value": "t̃ eouidobit omnis caro saluta",
        "format": "text/plain"
      },
      "target": {
        "source": "https://api.digitale-sammlungen.de/iiif/presentation/v2/bsb00034225/canvas/161",
        "selector": {
          "type": "FragmentSelector",
          "value": "xywh=98,2037,831,115"
        }
      }
    },
    {
      "id": "https://api.digitale-sammlungen.de/iiif/presentation/v2/bsb00034225/canvas/161#anno-51",
      "type": "Annotation",
      "motivation": "supplementing",
      "body": {
        "type": "TextualBody",
        "value": "et inde ẽ interior homo ipsa",
        "format": "text/plain"
      },
      "target": {
        "source": "https://api.digitale-sammlungen.de/iiif/presentation/v2/bsb00034225/canvas/161",
        "selector": {
          "type": "FragmentSelector",
          "value": "xywh=1076,1997,791,109"
        }
      }
    },
    {
      "id": "https://api.digitale-sammlungen.de/iiif/presentation/v2/bsb00034225/canvas/161#anno-52",
      "type": "Annotation",
      "motivation": "supplementing",
      "body": {
        "type": "TextualBody",
        "value": "raidinominis caro dictũ ẽ om̃s",
        "format": "text/plain"
      },
      "target": {
        "source": "https://api.digitale-sammlungen.de/iiif/presentation/v2/bsb00034225/canvas/161",
        "selector": {
          "type": "FragmentSelector",
          "value": "xywh=91,2114,832,107"
        }
      }
    },
    {
      "id": "https://api.digitale-sammlungen.de/iiif/presentation/v2/bsb00034225/canvas/161#anno-53",
      "type": "Annotation",
      "motivation": "supplementing",
      "body": {
        "type": "TextualBody",
        "value": "mens & anima rationalis ut apłs.",
        "format": "text/plain"
      },
      "target": {
        "source": "https://api.digitale-sammlungen.de/iiif/presentation/v2/bsb00034225/canvas/161",
        "selector": {
          "type": "FragmentSelector",
          "value": "xywh=1076,2069,851,113"
        }
      }
    },
    {
      "id": "https://api.digitale-sammlungen.de/iiif/presentation/v2/bsb00034225/canvas/161#anno-54",
      "type": "Annotation",
      "motivation": "supplementing",
      "body": {
        "type": "TextualBody",
        "value": "ihiunes. Solet in scã scriptura",
        "format": "text/plain"
      },
      "target": {
        "source": "https://api.digitale-sammlungen.de/iiif/presentation/v2/bsb00034225/canvas/161",
        "selector": {
          "type": "FragmentSelector",
          "value": "xywh=87,2189,866,113"
        }
      }
    },
    {
      "id": "https://api.digitale-sammlungen.de/iiif/presentation/v2/bsb00034225/canvas/161#anno-55",
      "type": "Annotation",
      "motivation": "supplementing",
      "body": {
        "type": "TextualBody",
        "value": "In interiore homine habitare",
        "format": "text/plain"
      },
      "target": {
        "source": "https://api.digitale-sammlungen.de/iiif/presentation/v2/bsb00034225/canvas/161",
        "selector": {
          "type": "FragmentSelector",
          "value": "xywh=1070,2142,778,109"
        }
      }
    },
    {
      "id": "https://api.digitale-sammlungen.de/iiif/presentation/v2/bsb00034225/canvas/161#anno-56",
      "type": "Annotation",
      "motivation": "supplementing",
      "body": {
        "type": "TextualBody",
        "value": "nomint. hominis rep̃hensio de",
        "format": "text/plain"
      },
      "target": {
        "source": "https://api.digitale-sammlungen.de/iiif/presentation/v2/bsb00034225/canvas/161",
        "selector": {
          "type": "FragmentSelector",
          "value": "xywh=91,2259,823,111"
        }
      }
    },
    {
      "id": "https://api.digitale-sammlungen.de/iiif/presentation/v2/bsb00034225/canvas/161#anno-57",
      "type": "Annotation",
      "motivation": "supplementing",
      "body": {
        "type": "TextualBody",
        "value": "xpm̃ ꝑfidẽ incordib urĩs.",
        "format": "text/plain"
      },
      "target": {
        "source": "https://api.digitale-sammlungen.de/iiif/presentation/v2/bsb00034225/canvas/161",
        "selector": {
          "type": "FragmentSelector",
          "value": "xywh=1066,2214,718,111"
        }
      }
    },
    {
      "id": "https://api.digitale-sammlungen.de/iiif/presentation/v2/bsb00034225/canvas/161#anno-58",
      "type": "Annotation",
      "motivation": "supplementing",
      "body": {
        "type": "TextualBody",
        "value": "signari ut apłs. Cũ enim sit int̃",
        "format": "text/plain"
      },
      "target": {
        "source": "https://api.digitale-sammlungen.de/iiif/presentation/v2/bsb00034225/canvas/161",
        "selector": {
          "type": "FragmentSelector",
          "value": "xywh=83,2344,840,96"
        }
      }
    },
    {
      "id": "https://api.digitale-sammlungen.de/iiif/presentation/v2/bsb00034225/canvas/161#anno-59",
      "type": "Annotation",
      "motivation": "supplementing",
      "body": {
        "type": "TextualBody",
        "value": "Anima in sacro eloquio & hominũ",
        "format": "text/plain"
      },
      "target": {
        "source": "https://api.digitale-sammlungen.de/iiif/presentation/v2/bsb00034225/canvas/161",
        "selector": {
          "type": "FragmentSelector",
          "value": "xywh=1012,2285,913,121"
        }
      }
    },
    {
      "id": "https://api.digitale-sammlungen.de/iiif/presentation/v2/bsb00034225/canvas/161#anno-60",
      "type": "Annotation",
      "motivation": "supplementing",
      "body": {
        "type": "TextualBody",
        "value": "uos Acdus et contentio. ñne car",
        "format": "text/plain"
      },
      "target": {
        "source": "https://api.digitale-sammlungen.de/iiif/presentation/v2/bsb00034225/canvas/161",
        "selector": {
          "type": "FragmentSelector",
          "value": "xywh=91,2415,836,100"
        }
      }
    },
    {
      "id": "https://api.digitale-sammlungen.de/iiif/presentation/v2/bsb00034225/canvas/161#anno-61",
      "type": "Annotation",
      "motivation": "supplementing",
      "body": {
        "type": "TextualBody",
        "value": "& ium̃torũ dr̃: sic̃ in libro bea",
        "format": "text/plain"
      },
      "target": {
        "source": "https://api.digitale-sammlungen.de/iiif/presentation/v2/bsb00034225/canvas/161",
        "selector": {
          "type": "FragmentSelector",
          "value": "xywh=1064,2368,842,104"
        }
      }
    },
    {
      "id": "https://api.digitale-sammlungen.de/iiif/presentation/v2/bsb00034225/canvas/161#anno-62",
      "type": "Annotation",
      "motivation": "supplementing",
      "body": {
        "type": "TextualBody",
        "value": "nales estis : ñne homines estis :",
        "format": "text/plain"
      },
      "target": {
        "source": "https://api.digitale-sammlungen.de/iiif/presentation/v2/bsb00034225/canvas/161",
        "selector": {
          "type": "FragmentSelector",
          "value": "xywh=91,2483,825,106"
        }
      }
    },
    {
      "id": "https://api.digitale-sammlungen.de/iiif/presentation/v2/bsb00034225/canvas/161#anno-63",
      "type": "Annotation",
      "motivation": "supplementing",
      "body": {
        "type": "TextualBody",
        "value": "ti iob legit᷑. Anima omnis uiuen",
        "format": "text/plain"
      },
      "target": {
        "source": "https://api.digitale-sammlungen.de/iiif/presentation/v2/bsb00034225/canvas/161",
        "selector": {
          "type": "FragmentSelector",
          "value": "xywh=1055,2438,853,111"
        }
      }
    },
    {
      "id": "https://api.digitale-sammlungen.de/iiif/presentation/v2/bsb00034225/canvas/161#anno-64",
      "type": "Annotation",
      "motivation": "supplementing",
      "body": {
        "type": "TextualBody",
        "value": "Et alibi. Inimicus homõ hoc fec̃.",
        "format": "text/plain"
      },
      "target": {
        "source": "https://api.digitale-sammlungen.de/iiif/presentation/v2/bsb00034225/canvas/161",
        "selector": {
          "type": "FragmentSelector",
          "value": "xywh=81,2555,865,107"
        }
      }
    },
    {
      "id": "https://api.digitale-sammlungen.de/iiif/presentation/v2/bsb00034225/canvas/161#anno-65",
      "type": "Annotation",
      "motivation": "supplementing",
      "body": {
        "type": "TextualBody",
        "value": "tis et sp̃c uniuiersȩ carnis in po",
        "format": "text/plain"
      },
      "target": {
        "source": "https://api.digitale-sammlungen.de/iiif/presentation/v2/bsb00034225/canvas/161",
        "selector": {
          "type": "FragmentSelector",
          "value": "xywh=1053,2517,797,111"
        }
      }
    },
    {
      "id": "https://api.digitale-sammlungen.de/iiif/presentation/v2/bsb00034225/canvas/161#anno-66",
      "type": "Annotation",
      "motivation": "supplementing",
      "body": {
        "type": "TextualBody",
        "value": "id ẽ diabolus. Et psalmista. Er",
        "format": "text/plain"
      },
      "target": {
        "source": "https://api.digitale-sammlungen.de/iiif/presentation/v2/bsb00034225/canvas/161",
        "selector": {
          "type": "FragmentSelector",
          "value": "xywh=89,2628,819,106"
        }
      }
    },
    {
      "id": "https://api.digitale-sammlungen.de/iiif/presentation/v2/bsb00034225/canvas/161#anno-67",
      "type": "Annotation",
      "motivation": "supplementing",
      "body": {
        "type": "TextualBody",
        "value": "testatt ẽ omnipotentis. Animã",
        "format": "text/plain"
      },
      "target": {
        "source": "https://api.digitale-sammlungen.de/iiif/presentation/v2/bsb00034225/canvas/161",
        "selector": {
          "type": "FragmentSelector",
          "value": "xywh=1051,2587,810,107"
        }
      }
    },
    {
      "id": "https://api.digitale-sammlungen.de/iiif/presentation/v2/bsb00034225/canvas/161#anno-68",
      "type": "Annotation",
      "motivation": "supplementing",
      "body": {
        "type": "TextualBody",
        "value": "urge dñe: ñ confortet᷑ homo. id",
        "format": "text/plain"
      },
      "target": {
        "source": "https://api.digitale-sammlungen.de/iiif/presentation/v2/bsb00034225/canvas/161",
        "selector": {
          "type": "FragmentSelector",
          "value": "xywh=85,2711,810,109"
        }
      }
    },
    {
      "id": "https://api.digitale-sammlungen.de/iiif/presentation/v2/bsb00034225/canvas/161#anno-69",
      "type": "Annotation",
      "motivation": "supplementing",
      "body": {
        "type": "TextualBody",
        "value": "rationale hominũ usq ad spũalẽ",
        "format": "text/plain"
      },
      "target": {
        "source": "https://api.digitale-sammlungen.de/iiif/presentation/v2/bsb00034225/canvas/161",
        "selector": {
          "type": "FragmentSelector",
          "value": "xywh=1049,2658,863,123"
        }
      }
    },
    {
      "id": "https://api.digitale-sammlungen.de/iiif/presentation/v2/bsb00034225/canvas/161#anno-70",
      "type": "Annotation",
      "motivation": "supplementing",
      "body": {
        "type": "TextualBody",
        "value": "ẽ antixp̃e: qui ab apło appellat᷑",
        "format": "text/plain"
      },
      "target": {
        "source": "https://api.digitale-sammlungen.de/iiif/presentation/v2/bsb00034225/canvas/161",
        "selector": {
          "type": "FragmentSelector",
          "value": "xywh=87,2794,832,100"
        }
      }
    },
    {
      "id": "https://api.digitale-sammlungen.de/iiif/presentation/v2/bsb00034225/canvas/161#anno-71",
      "type": "Annotation",
      "motivation": "supplementing",
      "body": {
        "type": "TextualBody",
        "value": "intellectũ subleuat. animã uͦ",
        "format": "text/plain"
      },
      "target": {
        "source": "https://api.digitale-sammlungen.de/iiif/presentation/v2/bsb00034225/canvas/161",
        "selector": {
          "type": "FragmentSelector",
          "value": "xywh=1053,2741,804,106"
        }
      }
    },
    {
      "id": "https://api.digitale-sammlungen.de/iiif/presentation/v2/bsb00034225/canvas/161#anno-72",
      "type": "Annotation",
      "motivation": "supplementing",
      "body": {
        "type": "TextualBody",
        "value": "homo peccati et filiꝰ ꝑditionis.",
        "format": "text/plain"
      },
      "target": {
        "source": "https://api.digitale-sammlungen.de/iiif/presentation/v2/bsb00034225/canvas/161",
        "selector": {
          "type": "FragmentSelector",
          "value": "xywh=81,2867,801,100"
        }
      }
    },
    {
      "id": "https://api.digitale-sammlungen.de/iiif/presentation/v2/bsb00034225/canvas/161#anno-73",
      "type": "Annotation",
      "motivation": "supplementing",
      "body": {
        "type": "TextualBody",
        "value": "irrationabiliũ usq ad corpore",
        "format": "text/plain"
      },
      "target": {
        "source": "https://api.digitale-sammlungen.de/iiif/presentation/v2/bsb00034225/canvas/161",
        "selector": {
          "type": "FragmentSelector",
          "value": "xywh=1049,2813,829,115"
        }
      }
    },
    {
      "id": "https://api.digitale-sammlungen.de/iiif/presentation/v2/bsb00034225/canvas/161#anno-74",
      "type": "Annotation",
      "motivation": "supplementing",
      "body": {
        "type": "TextualBody",
        "value": "Itẽ duplici sensu homo hic intel",
        "format": "text/plain"
      },
      "target": {
        "source": "https://api.digitale-sammlungen.de/iiif/presentation/v2/bsb00034225/canvas/161",
        "selector": {
          "type": "FragmentSelector",
          "value": "xywh=81,2937,831,104"
        }
      }
    },
    {
      "id": "https://api.digitale-sammlungen.de/iiif/presentation/v2/bsb00034225/canvas/161#anno-75",
      "type": "Annotation",
      "motivation": "supplementing",
      "body": {
        "type": "TextualBody",
        "value": "os sensus uiuificat. Sp̃s aliqͣn",
        "format": "text/plain"
      },
      "target": {
        "source": "https://api.digitale-sammlungen.de/iiif/presentation/v2/bsb00034225/canvas/161",
        "selector": {
          "type": "FragmentSelector",
          "value": "xywh=1049,2888,831,117"
        }
      }
    },
    {
      "id": "https://api.digitale-sammlungen.de/iiif/presentation/v2/bsb00034225/canvas/161#anno-76",
      "type": "Annotation",
      "motivation": "supplementing",
      "body": {
        "type": "TextualBody",
        "value": "ligitur. Factus ẽ. primus homo",
        "format": "text/plain"
      },
      "target": {
        "source": "https://api.digitale-sammlungen.de/iiif/presentation/v2/bsb00034225/canvas/161",
        "selector": {
          "type": "FragmentSelector",
          "value": "xywh=81,3007,801,105"
        }
      }
    },
    {
      "id": "https://api.digitale-sammlungen.de/iiif/presentation/v2/bsb00034225/canvas/161#anno-77",
      "type": "Annotation",
      "motivation": "supplementing",
      "body": {
        "type": "TextualBody",
        "value": "do ꝓ anima aliquando ꝓ effectu",
        "format": "text/plain"
      },
      "target": {
        "source": "https://api.digitale-sammlungen.de/iiif/presentation/v2/bsb00034225/canvas/161",
        "selector": {
          "type": "FragmentSelector",
          "value": "xywh=1046,2971,860,107"
        }
      }
    },
    {
      "id": "https://api.digitale-sammlungen.de/iiif/presentation/v2/bsb00034225/canvas/161#anno-78",
      "type": "Annotation",
      "motivation": "supplementing",
      "body": {
        "type": "TextualBody",
        "value": "adam inanimã. iuu̾enit̃. nouis",
        "format": "text/plain"
      },
      "target": {
        "source": "https://api.digitale-sammlungen.de/iiif/presentation/v2/bsb00034225/canvas/161",
        "selector": {
          "type": "FragmentSelector",
          "value": "xywh=81,3080,825,170"
        }
      }
    },
    {
      "id": "https://api.digitale-sammlungen.de/iiif/presentation/v2/bsb00034225/canvas/161#anno-79",
      "type": "Annotation",
      "motivation": "supplementing",
      "body": {
        "type": "TextualBody",
        "value": "spũali ponit᷑. ꝓ anima gͦ sp̃c dr̃:",
        "format": "text/plain"
      },
      "target": {
        "source": "https://api.digitale-sammlungen.de/iiif/presentation/v2/bsb00034225/canvas/161",
        "selector": {
          "type": "FragmentSelector",
          "value": "xywh=1042,3033,853,119"
        }
      }
    },
    {
      "id": "https://api.digitale-sammlungen.de/iiif/presentation/v2/bsb00034225/canvas/161#anno-80",
      "type": "Annotation",
      "motivation": "supplementing",
      "body": {
        "type": "TextualBody",
        "value": "sieut de nr̃o ipso capite ap̃o",
        "format": "text/plain"
      },
      "target": {
        "source": "https://api.digitale-sammlungen.de/iiif/presentation/v2/bsb00034225/canvas/161",
        "selector": {
          "type": "FragmentSelector",
          "value": "xywh=1042,3110,770,166"
        }
      }
    },
    {
      "id": "https://api.digitale-sammlungen.de/iiif/presentation/v2/bsb00034225/canvas/161#anno-81",
      "type": "Annotation",
      "motivation": "supplementing",
      "body": {
        "type": "TextualBody",
        "value": "10",
        "format": "text/plain"
      },
      "target": {
        "source": "https://api.digitale-sammlungen.de/iiif/presentation/v2/bsb00034225/canvas/161",
        "selector": {
          "type": "FragmentSelector",
          "value": "xywh=2281,127,107,88"
        }
      }
    }
  ]
}